{"status":"success","message":"The DATA_COMP field for indicator 2-1-1, translated into all languages","data":{"en":"Ratio of households 1) has minimal food consumption, but unable to meet certain essential non-food expenses without depleting livelihoods, 2) with poor food consumption, or,\nMarginal capacity to meet minimum food needs only through accelerated exhaustion of livelihoods, 3) with significant deficiency in food consumption, or,\nExtreme loss of livelihood resulting in severe deficiencies in food consumption, or worse and the total number of households, multiplied by 100","fr":"Rapport entre les ménages 1)dispose d’une consommation alimentaire minimale, mais incapable d’assurer certaines dépenses essentielles non alimentaires sans épuiser les moyens d’existence, 2) avec déficience de consommation alimentaire, ou,\nCapacité marginale d’assurer besoins alimentaires minimaux seulement à travers l’épuisement accéléré des moyens d’existence, 3) avec une importante déficience de la consommation alimentaire, ou,\nPerte extrême des moyens d’existence aboutissant à d’importantes déficiences de consommation alimentaire, ou pire et le nombre total de ménages, multiplié par 100"}}