<?xml version="1.0" encoding="utf-8"?>
<mes:GenericMetadata xmlns:mes="http://www.sdmx.org/resources/sdmxml/schemas/v2_1/message" xmlns:gen="http://www.sdmx.org/resources/sdmxml/schemas/v2_1/metadata/generic" xmlns:com="http://www.sdmx.org/resources/sdmxml/schemas/v2_1/common">
  <mes:Header>
    <mes:ID>MESSAGE_ID_PLACEHOLDER</mes:ID>
    <mes:Test>false</mes:Test>
    <mes:Prepared>2021-08-01T18:39:10.869Z</mes:Prepared>
    <mes:Sender id="sender"/>
    <mes:Structure structureID="MDS1">
      <com:Structure>
        <URN>urn:sdmx:org.sdmx.infomodel.metadatastructure.MetadataStructure=IAEG-SDGs:SDG_MSD(0.3)</URN>
      </com:Structure>
    </mes:Structure>
  </mes:Header>
  <mes:MetadataSet structureRef="MDS1" setID="8b939d6b-b227-4b06-9676-e6926b1a309d">
    <com:Name xml:lang="en">SDG METADATA SET</com:Name>
    <gen:Report id="SDG_META_RPT">
      <gen:Target id="KEY_TARGET">
        <gen:ReferenceValue id="DIMENSION_DESCRIPTOR_VALUES_TARGET">
          <gen:DataKey>
            <com:KeyValue id="SERIES">
              <com:Value>SE_GPI_PART</com:Value>
            </com:KeyValue>
            <com:KeyValue id="REPORTING_TYPE">
              <com:Value>N</com:Value>
            </com:KeyValue>
            <com:KeyValue id="REF_AREA">
              <com:Value>BI</com:Value>
            </com:KeyValue>
          </gen:DataKey>
        </gen:ReferenceValue>
        <gen:ReferenceValue id="Dataflow">
          <gen:ObjectReference>
            <URN>urn:sdmx:org.sdmx.infomodel.datastructure.Dataflow=IAEG-SDGs:DF_SDG_GLC(1.0)</URN>
          </gen:ObjectReference>
        </gen:ReferenceValue>
      </gen:Target>
      <gen:AttributeSet>
        <gen:ReportedAttribute id="SDG_INDICATOR_INFO">
          <com:Text xml:lang="en"/>
        </gen:ReportedAttribute>
        <gen:ReportedAttribute id="SDG_GOAL">
          <com:Text xml:lang="en"/>
        </gen:ReportedAttribute>
        <gen:ReportedAttribute id="SDG_TARGET">
          <com:Text xml:lang="en"/>
        </gen:ReportedAttribute>
        <gen:ReportedAttribute id="SDG_INDICATOR">
          <com:Text xml:lang="en"/>
        </gen:ReportedAttribute>
        <gen:ReportedAttribute id="SDG_SERIES_DESCR">
          <com:Text xml:lang="en"/>
        </gen:ReportedAttribute>
        <gen:ReportedAttribute id="META_LAST_UPDATE">
          <com:Text xml:lang="en"/>
        </gen:ReportedAttribute>
        <gen:ReportedAttribute id="SDG_RELATED_INDICATORS">
          <com:Text xml:lang="en"/>
        </gen:ReportedAttribute>
        <gen:ReportedAttribute id="SDG_CUSTODIAN_AGENCIES">
          <com:Text xml:lang="en"/>
        </gen:ReportedAttribute>
        <gen:ReportedAttribute id="CONTACT">
          <com:Text xml:lang="en"/>
        </gen:ReportedAttribute>
        <gen:ReportedAttribute id="CONTACT_ORGANISATION">
          <com:Text xml:lang="en"/>
        </gen:ReportedAttribute>
        <gen:ReportedAttribute id="CONTACT_NAME">
          <com:Text xml:lang="en"/>
        </gen:ReportedAttribute>
        <gen:ReportedAttribute id="ORGANISATION_UNIT">
          <com:Text xml:lang="en"/>
        </gen:ReportedAttribute>
        <gen:ReportedAttribute id="CONTACT_FUNCT">
          <com:Text xml:lang="en"/>
        </gen:ReportedAttribute>
        <gen:ReportedAttribute id="CONTACT_PHONE">
          <com:Text xml:lang="en"/>
        </gen:ReportedAttribute>
        <gen:ReportedAttribute id="CONTACT_MAIL">
          <com:Text xml:lang="en"/>
        </gen:ReportedAttribute>
        <gen:ReportedAttribute id="CONTACT_EMAIL">
          <com:Text xml:lang="en"/>
        </gen:ReportedAttribute>
        <gen:ReportedAttribute id="IND_DEF_CON_CLASS">
          <com:Text xml:lang="en"/>
        </gen:ReportedAttribute>
        <gen:ReportedAttribute id="STAT_CONC_DEF">
          <com:Text xml:lang="en"/>
        </gen:ReportedAttribute>
        <gen:ReportedAttribute id="UNIT_MEASURE">
          <com:Text xml:lang="en"/>
        </gen:ReportedAttribute>
        <gen:ReportedAttribute id="CLASS_SYSTEM">
          <com:Text xml:lang="en"/>
        </gen:ReportedAttribute>
        <gen:ReportedAttribute id="SRC_TYPE_COLL_METHOD">
          <com:Text xml:lang="en"/>
        </gen:ReportedAttribute>
        <gen:ReportedAttribute id="SOURCE_TYPE">
          <com:Text xml:lang="en"/>
        </gen:ReportedAttribute>
        <gen:ReportedAttribute id="COLL_METHOD">
          <com:Text xml:lang="en"/>
        </gen:ReportedAttribute>
        <gen:ReportedAttribute id="FREQ_COLL">
          <com:Text xml:lang="en"/>
        </gen:ReportedAttribute>
        <gen:ReportedAttribute id="REL_CAL_POLICY">
          <com:Text xml:lang="en"/>
        </gen:ReportedAttribute>
        <gen:ReportedAttribute id="DATA_SOURCE">
          <com:Text xml:lang="en"/>
        </gen:ReportedAttribute>
        <gen:ReportedAttribute id="COMPILING_ORG">
          <com:Text xml:lang="en"/>
        </gen:ReportedAttribute>
        <gen:ReportedAttribute id="INST_MANDATE">
          <com:Text xml:lang="en"/>
        </gen:ReportedAttribute>
        <gen:ReportedAttribute id="OTHER_METHOD">
          <com:Text xml:lang="en"/>
        </gen:ReportedAttribute>
        <gen:ReportedAttribute id="RATIONALE">
          <com:Text xml:lang="en"/>
        </gen:ReportedAttribute>
        <gen:ReportedAttribute id="REC_USE_LIM">
          <com:Text xml:lang="en"/>
        </gen:ReportedAttribute>
        <gen:ReportedAttribute id="DATA_COMP">
          <com:Text xml:lang="en"/>
        </gen:ReportedAttribute>
        <gen:ReportedAttribute id="DATA_VALIDATION">
          <com:Text xml:lang="en"/>
        </gen:ReportedAttribute>
        <gen:ReportedAttribute id="ADJUSTMENT">
          <com:Text xml:lang="en"/>
        </gen:ReportedAttribute>
        <gen:ReportedAttribute id="IMPUTATION">
          <com:Text xml:lang="en"/>
        </gen:ReportedAttribute>
        <gen:ReportedAttribute id="REG_AGG">
          <com:Text xml:lang="en"/>
        </gen:ReportedAttribute>
        <gen:ReportedAttribute id="DOC_METHOD">
          <com:Text xml:lang="en"/>
        </gen:ReportedAttribute>
        <gen:ReportedAttribute id="QUALITY_MGMNT">
          <com:Text xml:lang="en"/>
        </gen:ReportedAttribute>
        <gen:ReportedAttribute id="QUALITY_ASSURE">
          <com:Text xml:lang="en"/>
        </gen:ReportedAttribute>
        <gen:ReportedAttribute id="QUALITY_ASSMNT">
          <com:Text xml:lang="en"/>
        </gen:ReportedAttribute>
        <gen:ReportedAttribute id="COVERAGE">
          <com:Text xml:lang="en"/>
        </gen:ReportedAttribute>
        <gen:ReportedAttribute id="COMPARABILITY">
          <com:Text xml:lang="en"/>
        </gen:ReportedAttribute>
        <gen:ReportedAttribute id="OTHER_DOC">
          <com:Text xml:lang="en"/>
        </gen:ReportedAttribute>
      </gen:AttributeSet>
    </gen:Report>
  </mes:MetadataSet>
  <mes:MetadataSet structureRef="MDS1" setID="ddf75337-2e01-4acd-b080-25033e5fb1e9">
    <com:Name xml:lang="en">SDG METADATA SET</com:Name>
    <gen:Report id="SDG_META_RPT">
      <gen:Target id="KEY_TARGET">
        <gen:ReferenceValue id="DIMENSION_DESCRIPTOR_VALUES_TARGET">
          <gen:DataKey>
            <com:KeyValue id="SERIES">
              <com:Value>SE_GPI_ICTS</com:Value>
            </com:KeyValue>
            <com:KeyValue id="REPORTING_TYPE">
              <com:Value>N</com:Value>
            </com:KeyValue>
            <com:KeyValue id="REF_AREA">
              <com:Value>BI</com:Value>
            </com:KeyValue>
          </gen:DataKey>
        </gen:ReferenceValue>
        <gen:ReferenceValue id="Dataflow">
          <gen:ObjectReference>
            <URN>urn:sdmx:org.sdmx.infomodel.datastructure.Dataflow=IAEG-SDGs:DF_SDG_GLC(1.0)</URN>
          </gen:ObjectReference>
        </gen:ReferenceValue>
      </gen:Target>
      <gen:AttributeSet>
        <gen:ReportedAttribute id="SDG_INDICATOR_INFO">
          <com:Text xml:lang="en"/>
        </gen:ReportedAttribute>
        <gen:ReportedAttribute id="SDG_GOAL">
          <com:Text xml:lang="en"/>
        </gen:ReportedAttribute>
        <gen:ReportedAttribute id="SDG_TARGET">
          <com:Text xml:lang="en"/>
        </gen:ReportedAttribute>
        <gen:ReportedAttribute id="SDG_INDICATOR">
          <com:Text xml:lang="en"/>
        </gen:ReportedAttribute>
        <gen:ReportedAttribute id="SDG_SERIES_DESCR">
          <com:Text xml:lang="en"/>
        </gen:ReportedAttribute>
        <gen:ReportedAttribute id="META_LAST_UPDATE">
          <com:Text xml:lang="en"/>
        </gen:ReportedAttribute>
        <gen:ReportedAttribute id="SDG_RELATED_INDICATORS">
          <com:Text xml:lang="en"/>
        </gen:ReportedAttribute>
        <gen:ReportedAttribute id="SDG_CUSTODIAN_AGENCIES">
          <com:Text xml:lang="en"/>
        </gen:ReportedAttribute>
        <gen:ReportedAttribute id="CONTACT">
          <com:Text xml:lang="en"/>
        </gen:ReportedAttribute>
        <gen:ReportedAttribute id="CONTACT_ORGANISATION">
          <com:Text xml:lang="en"/>
        </gen:ReportedAttribute>
        <gen:ReportedAttribute id="CONTACT_NAME">
          <com:Text xml:lang="en"/>
        </gen:ReportedAttribute>
        <gen:ReportedAttribute id="ORGANISATION_UNIT">
          <com:Text xml:lang="en"/>
        </gen:ReportedAttribute>
        <gen:ReportedAttribute id="CONTACT_FUNCT">
          <com:Text xml:lang="en"/>
        </gen:ReportedAttribute>
        <gen:ReportedAttribute id="CONTACT_PHONE">
          <com:Text xml:lang="en"/>
        </gen:ReportedAttribute>
        <gen:ReportedAttribute id="CONTACT_MAIL">
          <com:Text xml:lang="en"/>
        </gen:ReportedAttribute>
        <gen:ReportedAttribute id="CONTACT_EMAIL">
          <com:Text xml:lang="en"/>
        </gen:ReportedAttribute>
        <gen:ReportedAttribute id="IND_DEF_CON_CLASS">
          <com:Text xml:lang="en"/>
        </gen:ReportedAttribute>
        <gen:ReportedAttribute id="STAT_CONC_DEF">
          <com:Text xml:lang="en"/>
        </gen:ReportedAttribute>
        <gen:ReportedAttribute id="UNIT_MEASURE">
          <com:Text xml:lang="en"/>
        </gen:ReportedAttribute>
        <gen:ReportedAttribute id="CLASS_SYSTEM">
          <com:Text xml:lang="en"/>
        </gen:ReportedAttribute>
        <gen:ReportedAttribute id="SRC_TYPE_COLL_METHOD">
          <com:Text xml:lang="en"/>
        </gen:ReportedAttribute>
        <gen:ReportedAttribute id="SOURCE_TYPE">
          <com:Text xml:lang="en"/>
        </gen:ReportedAttribute>
        <gen:ReportedAttribute id="COLL_METHOD">
          <com:Text xml:lang="en"/>
        </gen:ReportedAttribute>
        <gen:ReportedAttribute id="FREQ_COLL">
          <com:Text xml:lang="en"/>
        </gen:ReportedAttribute>
        <gen:ReportedAttribute id="REL_CAL_POLICY">
          <com:Text xml:lang="en"/>
        </gen:ReportedAttribute>
        <gen:ReportedAttribute id="DATA_SOURCE">
          <com:Text xml:lang="en"/>
        </gen:ReportedAttribute>
        <gen:ReportedAttribute id="COMPILING_ORG">
          <com:Text xml:lang="en"/>
        </gen:ReportedAttribute>
        <gen:ReportedAttribute id="INST_MANDATE">
          <com:Text xml:lang="en"/>
        </gen:ReportedAttribute>
        <gen:ReportedAttribute id="OTHER_METHOD">
          <com:Text xml:lang="en"/>
        </gen:ReportedAttribute>
        <gen:ReportedAttribute id="RATIONALE">
          <com:Text xml:lang="en"/>
        </gen:ReportedAttribute>
        <gen:ReportedAttribute id="REC_USE_LIM">
          <com:Text xml:lang="en"/>
        </gen:ReportedAttribute>
        <gen:ReportedAttribute id="DATA_COMP">
          <com:Text xml:lang="en"/>
        </gen:ReportedAttribute>
        <gen:ReportedAttribute id="DATA_VALIDATION">
          <com:Text xml:lang="en"/>
        </gen:ReportedAttribute>
        <gen:ReportedAttribute id="ADJUSTMENT">
          <com:Text xml:lang="en"/>
        </gen:ReportedAttribute>
        <gen:ReportedAttribute id="IMPUTATION">
          <com:Text xml:lang="en"/>
        </gen:ReportedAttribute>
        <gen:ReportedAttribute id="REG_AGG">
          <com:Text xml:lang="en"/>
        </gen:ReportedAttribute>
        <gen:ReportedAttribute id="DOC_METHOD">
          <com:Text xml:lang="en"/>
        </gen:ReportedAttribute>
        <gen:ReportedAttribute id="QUALITY_MGMNT">
          <com:Text xml:lang="en"/>
        </gen:ReportedAttribute>
        <gen:ReportedAttribute id="QUALITY_ASSURE">
          <com:Text xml:lang="en"/>
        </gen:ReportedAttribute>
        <gen:ReportedAttribute id="QUALITY_ASSMNT">
          <com:Text xml:lang="en"/>
        </gen:ReportedAttribute>
        <gen:ReportedAttribute id="COVERAGE">
          <com:Text xml:lang="en"/>
        </gen:ReportedAttribute>
        <gen:ReportedAttribute id="COMPARABILITY">
          <com:Text xml:lang="en"/>
        </gen:ReportedAttribute>
        <gen:ReportedAttribute id="OTHER_DOC">
          <com:Text xml:lang="en"/>
        </gen:ReportedAttribute>
      </gen:AttributeSet>
    </gen:Report>
  </mes:MetadataSet>
  <mes:MetadataSet structureRef="MDS1" setID="c23e2b83-f636-4a5b-939c-1cda93175961">
    <com:Name xml:lang="en">SDG METADATA SET</com:Name>
    <gen:Report id="SDG_META_RPT">
      <gen:Target id="KEY_TARGET">
        <gen:ReferenceValue id="DIMENSION_DESCRIPTOR_VALUES_TARGET">
          <gen:DataKey>
            <com:KeyValue id="SERIES">
              <com:Value>SE_NAP_ACHI</com:Value>
            </com:KeyValue>
            <com:KeyValue id="REPORTING_TYPE">
              <com:Value>N</com:Value>
            </com:KeyValue>
            <com:KeyValue id="REF_AREA">
              <com:Value>BI</com:Value>
            </com:KeyValue>
          </gen:DataKey>
        </gen:ReferenceValue>
        <gen:ReferenceValue id="Dataflow">
          <gen:ObjectReference>
            <URN>urn:sdmx:org.sdmx.infomodel.datastructure.Dataflow=IAEG-SDGs:DF_SDG_GLC(1.0)</URN>
          </gen:ObjectReference>
        </gen:ReferenceValue>
      </gen:Target>
      <gen:AttributeSet>
        <gen:ReportedAttribute id="SDG_INDICATOR_INFO">
          <com:Text xml:lang="en"/>
        </gen:ReportedAttribute>
        <gen:ReportedAttribute id="SDG_GOAL">
          <com:Text xml:lang="en"/>
        </gen:ReportedAttribute>
        <gen:ReportedAttribute id="SDG_TARGET">
          <com:Text xml:lang="en"/>
        </gen:ReportedAttribute>
        <gen:ReportedAttribute id="SDG_INDICATOR">
          <com:Text xml:lang="en"/>
        </gen:ReportedAttribute>
        <gen:ReportedAttribute id="SDG_SERIES_DESCR">
          <com:Text xml:lang="en"/>
        </gen:ReportedAttribute>
        <gen:ReportedAttribute id="META_LAST_UPDATE">
          <com:Text xml:lang="en"/>
        </gen:ReportedAttribute>
        <gen:ReportedAttribute id="SDG_RELATED_INDICATORS">
          <com:Text xml:lang="en"/>
        </gen:ReportedAttribute>
        <gen:ReportedAttribute id="SDG_CUSTODIAN_AGENCIES">
          <com:Text xml:lang="en"/>
        </gen:ReportedAttribute>
        <gen:ReportedAttribute id="CONTACT">
          <com:Text xml:lang="en"/>
        </gen:ReportedAttribute>
        <gen:ReportedAttribute id="CONTACT_ORGANISATION">
          <com:Text xml:lang="en"/>
        </gen:ReportedAttribute>
        <gen:ReportedAttribute id="CONTACT_NAME">
          <com:Text xml:lang="en"/>
        </gen:ReportedAttribute>
        <gen:ReportedAttribute id="ORGANISATION_UNIT">
          <com:Text xml:lang="en"/>
        </gen:ReportedAttribute>
        <gen:ReportedAttribute id="CONTACT_FUNCT">
          <com:Text xml:lang="en"/>
        </gen:ReportedAttribute>
        <gen:ReportedAttribute id="CONTACT_PHONE">
          <com:Text xml:lang="en"/>
        </gen:ReportedAttribute>
        <gen:ReportedAttribute id="CONTACT_MAIL">
          <com:Text xml:lang="en"/>
        </gen:ReportedAttribute>
        <gen:ReportedAttribute id="CONTACT_EMAIL">
          <com:Text xml:lang="en"/>
        </gen:ReportedAttribute>
        <gen:ReportedAttribute id="IND_DEF_CON_CLASS">
          <com:Text xml:lang="en"/>
        </gen:ReportedAttribute>
        <gen:ReportedAttribute id="STAT_CONC_DEF">
          <com:Text xml:lang="en"/>
        </gen:ReportedAttribute>
        <gen:ReportedAttribute id="UNIT_MEASURE">
          <com:Text xml:lang="en"/>
        </gen:ReportedAttribute>
        <gen:ReportedAttribute id="CLASS_SYSTEM">
          <com:Text xml:lang="en"/>
        </gen:ReportedAttribute>
        <gen:ReportedAttribute id="SRC_TYPE_COLL_METHOD">
          <com:Text xml:lang="en"/>
        </gen:ReportedAttribute>
        <gen:ReportedAttribute id="SOURCE_TYPE">
          <com:Text xml:lang="en"/>
        </gen:ReportedAttribute>
        <gen:ReportedAttribute id="COLL_METHOD">
          <com:Text xml:lang="en"/>
        </gen:ReportedAttribute>
        <gen:ReportedAttribute id="FREQ_COLL">
          <com:Text xml:lang="en"/>
        </gen:ReportedAttribute>
        <gen:ReportedAttribute id="REL_CAL_POLICY">
          <com:Text xml:lang="en"/>
        </gen:ReportedAttribute>
        <gen:ReportedAttribute id="DATA_SOURCE">
          <com:Text xml:lang="en"/>
        </gen:ReportedAttribute>
        <gen:ReportedAttribute id="COMPILING_ORG">
          <com:Text xml:lang="en"/>
        </gen:ReportedAttribute>
        <gen:ReportedAttribute id="INST_MANDATE">
          <com:Text xml:lang="en"/>
        </gen:ReportedAttribute>
        <gen:ReportedAttribute id="OTHER_METHOD">
          <com:Text xml:lang="en"/>
        </gen:ReportedAttribute>
        <gen:ReportedAttribute id="RATIONALE">
          <com:Text xml:lang="en"/>
        </gen:ReportedAttribute>
        <gen:ReportedAttribute id="REC_USE_LIM">
          <com:Text xml:lang="en"/>
        </gen:ReportedAttribute>
        <gen:ReportedAttribute id="DATA_COMP">
          <com:Text xml:lang="en"/>
        </gen:ReportedAttribute>
        <gen:ReportedAttribute id="DATA_VALIDATION">
          <com:Text xml:lang="en"/>
        </gen:ReportedAttribute>
        <gen:ReportedAttribute id="ADJUSTMENT">
          <com:Text xml:lang="en"/>
        </gen:ReportedAttribute>
        <gen:ReportedAttribute id="IMPUTATION">
          <com:Text xml:lang="en"/>
        </gen:ReportedAttribute>
        <gen:ReportedAttribute id="REG_AGG">
          <com:Text xml:lang="en"/>
        </gen:ReportedAttribute>
        <gen:ReportedAttribute id="DOC_METHOD">
          <com:Text xml:lang="en"/>
        </gen:ReportedAttribute>
        <gen:ReportedAttribute id="QUALITY_MGMNT">
          <com:Text xml:lang="en"/>
        </gen:ReportedAttribute>
        <gen:ReportedAttribute id="QUALITY_ASSURE">
          <com:Text xml:lang="en"/>
        </gen:ReportedAttribute>
        <gen:ReportedAttribute id="QUALITY_ASSMNT">
          <com:Text xml:lang="en"/>
        </gen:ReportedAttribute>
        <gen:ReportedAttribute id="COVERAGE">
          <com:Text xml:lang="en"/>
        </gen:ReportedAttribute>
        <gen:ReportedAttribute id="COMPARABILITY">
          <com:Text xml:lang="en"/>
        </gen:ReportedAttribute>
        <gen:ReportedAttribute id="OTHER_DOC">
          <com:Text xml:lang="en"/>
        </gen:ReportedAttribute>
      </gen:AttributeSet>
    </gen:Report>
  </mes:MetadataSet>
  <mes:MetadataSet structureRef="MDS1" setID="c7f4c840-c478-4da1-a4d7-adbb6c7109fe">
    <com:Name xml:lang="en">SDG METADATA SET</com:Name>
    <gen:Report id="SDG_META_RPT">
      <gen:Target id="KEY_TARGET">
        <gen:ReferenceValue id="DIMENSION_DESCRIPTOR_VALUES_TARGET">
          <gen:DataKey>
            <com:KeyValue id="SERIES">
              <com:Value>SE_LGP_ACHI</com:Value>
            </com:KeyValue>
            <com:KeyValue id="REPORTING_TYPE">
              <com:Value>N</com:Value>
            </com:KeyValue>
            <com:KeyValue id="REF_AREA">
              <com:Value>BI</com:Value>
            </com:KeyValue>
          </gen:DataKey>
        </gen:ReferenceValue>
        <gen:ReferenceValue id="Dataflow">
          <gen:ObjectReference>
            <URN>urn:sdmx:org.sdmx.infomodel.datastructure.Dataflow=IAEG-SDGs:DF_SDG_GLC(1.0)</URN>
          </gen:ObjectReference>
        </gen:ReferenceValue>
      </gen:Target>
      <gen:AttributeSet>
        <gen:ReportedAttribute id="SDG_INDICATOR_INFO">
          <com:Text xml:lang="en"/>
        </gen:ReportedAttribute>
        <gen:ReportedAttribute id="SDG_GOAL">
          <com:Text xml:lang="en"/>
        </gen:ReportedAttribute>
        <gen:ReportedAttribute id="SDG_TARGET">
          <com:Text xml:lang="en"/>
        </gen:ReportedAttribute>
        <gen:ReportedAttribute id="SDG_INDICATOR">
          <com:Text xml:lang="en"/>
        </gen:ReportedAttribute>
        <gen:ReportedAttribute id="SDG_SERIES_DESCR">
          <com:Text xml:lang="en"/>
        </gen:ReportedAttribute>
        <gen:ReportedAttribute id="META_LAST_UPDATE">
          <com:Text xml:lang="en"/>
        </gen:ReportedAttribute>
        <gen:ReportedAttribute id="SDG_RELATED_INDICATORS">
          <com:Text xml:lang="en"/>
        </gen:ReportedAttribute>
        <gen:ReportedAttribute id="SDG_CUSTODIAN_AGENCIES">
          <com:Text xml:lang="en"/>
        </gen:ReportedAttribute>
        <gen:ReportedAttribute id="CONTACT">
          <com:Text xml:lang="en"/>
        </gen:ReportedAttribute>
        <gen:ReportedAttribute id="CONTACT_ORGANISATION">
          <com:Text xml:lang="en"/>
        </gen:ReportedAttribute>
        <gen:ReportedAttribute id="CONTACT_NAME">
          <com:Text xml:lang="en"/>
        </gen:ReportedAttribute>
        <gen:ReportedAttribute id="ORGANISATION_UNIT">
          <com:Text xml:lang="en"/>
        </gen:ReportedAttribute>
        <gen:ReportedAttribute id="CONTACT_FUNCT">
          <com:Text xml:lang="en"/>
        </gen:ReportedAttribute>
        <gen:ReportedAttribute id="CONTACT_PHONE">
          <com:Text xml:lang="en"/>
        </gen:ReportedAttribute>
        <gen:ReportedAttribute id="CONTACT_MAIL">
          <com:Text xml:lang="en"/>
        </gen:ReportedAttribute>
        <gen:ReportedAttribute id="CONTACT_EMAIL">
          <com:Text xml:lang="en"/>
        </gen:ReportedAttribute>
        <gen:ReportedAttribute id="IND_DEF_CON_CLASS">
          <com:Text xml:lang="en"/>
        </gen:ReportedAttribute>
        <gen:ReportedAttribute id="STAT_CONC_DEF">
          <com:Text xml:lang="en"/>
        </gen:ReportedAttribute>
        <gen:ReportedAttribute id="UNIT_MEASURE">
          <com:Text xml:lang="en"/>
        </gen:ReportedAttribute>
        <gen:ReportedAttribute id="CLASS_SYSTEM">
          <com:Text xml:lang="en"/>
        </gen:ReportedAttribute>
        <gen:ReportedAttribute id="SRC_TYPE_COLL_METHOD">
          <com:Text xml:lang="en"/>
        </gen:ReportedAttribute>
        <gen:ReportedAttribute id="SOURCE_TYPE">
          <com:Text xml:lang="en"/>
        </gen:ReportedAttribute>
        <gen:ReportedAttribute id="COLL_METHOD">
          <com:Text xml:lang="en"/>
        </gen:ReportedAttribute>
        <gen:ReportedAttribute id="FREQ_COLL">
          <com:Text xml:lang="en"/>
        </gen:ReportedAttribute>
        <gen:ReportedAttribute id="REL_CAL_POLICY">
          <com:Text xml:lang="en"/>
        </gen:ReportedAttribute>
        <gen:ReportedAttribute id="DATA_SOURCE">
          <com:Text xml:lang="en"/>
        </gen:ReportedAttribute>
        <gen:ReportedAttribute id="COMPILING_ORG">
          <com:Text xml:lang="en"/>
        </gen:ReportedAttribute>
        <gen:ReportedAttribute id="INST_MANDATE">
          <com:Text xml:lang="en"/>
        </gen:ReportedAttribute>
        <gen:ReportedAttribute id="OTHER_METHOD">
          <com:Text xml:lang="en"/>
        </gen:ReportedAttribute>
        <gen:ReportedAttribute id="RATIONALE">
          <com:Text xml:lang="en"/>
        </gen:ReportedAttribute>
        <gen:ReportedAttribute id="REC_USE_LIM">
          <com:Text xml:lang="en"/>
        </gen:ReportedAttribute>
        <gen:ReportedAttribute id="DATA_COMP">
          <com:Text xml:lang="en"/>
        </gen:ReportedAttribute>
        <gen:ReportedAttribute id="DATA_VALIDATION">
          <com:Text xml:lang="en"/>
        </gen:ReportedAttribute>
        <gen:ReportedAttribute id="ADJUSTMENT">
          <com:Text xml:lang="en"/>
        </gen:ReportedAttribute>
        <gen:ReportedAttribute id="IMPUTATION">
          <com:Text xml:lang="en"/>
        </gen:ReportedAttribute>
        <gen:ReportedAttribute id="REG_AGG">
          <com:Text xml:lang="en"/>
        </gen:ReportedAttribute>
        <gen:ReportedAttribute id="DOC_METHOD">
          <com:Text xml:lang="en"/>
        </gen:ReportedAttribute>
        <gen:ReportedAttribute id="QUALITY_MGMNT">
          <com:Text xml:lang="en"/>
        </gen:ReportedAttribute>
        <gen:ReportedAttribute id="QUALITY_ASSURE">
          <com:Text xml:lang="en"/>
        </gen:ReportedAttribute>
        <gen:ReportedAttribute id="QUALITY_ASSMNT">
          <com:Text xml:lang="en"/>
        </gen:ReportedAttribute>
        <gen:ReportedAttribute id="COVERAGE">
          <com:Text xml:lang="en"/>
        </gen:ReportedAttribute>
        <gen:ReportedAttribute id="COMPARABILITY">
          <com:Text xml:lang="en"/>
        </gen:ReportedAttribute>
        <gen:ReportedAttribute id="OTHER_DOC">
          <com:Text xml:lang="en"/>
        </gen:ReportedAttribute>
      </gen:AttributeSet>
    </gen:Report>
  </mes:MetadataSet>
  <mes:MetadataSet structureRef="MDS1" setID="501a6db9-b520-46f4-9a23-8eb108a41e4d">
    <com:Name xml:lang="en">SDG METADATA SET</com:Name>
    <gen:Report id="SDG_META_RPT">
      <gen:Target id="KEY_TARGET">
        <gen:ReferenceValue id="DIMENSION_DESCRIPTOR_VALUES_TARGET">
          <gen:DataKey>
            <com:KeyValue id="SERIES">
              <com:Value>SE_IMP_FPOF</com:Value>
            </com:KeyValue>
            <com:KeyValue id="REPORTING_TYPE">
              <com:Value>N</com:Value>
            </com:KeyValue>
            <com:KeyValue id="REF_AREA">
              <com:Value>BI</com:Value>
            </com:KeyValue>
          </gen:DataKey>
        </gen:ReferenceValue>
        <gen:ReferenceValue id="Dataflow">
          <gen:ObjectReference>
            <URN>urn:sdmx:org.sdmx.infomodel.datastructure.Dataflow=IAEG-SDGs:DF_SDG_GLC(1.0)</URN>
          </gen:ObjectReference>
        </gen:ReferenceValue>
      </gen:Target>
      <gen:AttributeSet>
        <gen:ReportedAttribute id="SDG_INDICATOR_INFO">
          <com:Text xml:lang="en"/>
        </gen:ReportedAttribute>
        <gen:ReportedAttribute id="SDG_GOAL">
          <com:Text xml:lang="en"/>
        </gen:ReportedAttribute>
        <gen:ReportedAttribute id="SDG_TARGET">
          <com:Text xml:lang="en"/>
        </gen:ReportedAttribute>
        <gen:ReportedAttribute id="SDG_INDICATOR">
          <com:Text xml:lang="en"/>
        </gen:ReportedAttribute>
        <gen:ReportedAttribute id="SDG_SERIES_DESCR">
          <com:Text xml:lang="en"/>
        </gen:ReportedAttribute>
        <gen:ReportedAttribute id="META_LAST_UPDATE">
          <com:Text xml:lang="en"/>
        </gen:ReportedAttribute>
        <gen:ReportedAttribute id="SDG_RELATED_INDICATORS">
          <com:Text xml:lang="en"/>
        </gen:ReportedAttribute>
        <gen:ReportedAttribute id="SDG_CUSTODIAN_AGENCIES">
          <com:Text xml:lang="en"/>
        </gen:ReportedAttribute>
        <gen:ReportedAttribute id="CONTACT">
          <com:Text xml:lang="en"/>
        </gen:ReportedAttribute>
        <gen:ReportedAttribute id="CONTACT_ORGANISATION">
          <com:Text xml:lang="en"/>
        </gen:ReportedAttribute>
        <gen:ReportedAttribute id="CONTACT_NAME">
          <com:Text xml:lang="en"/>
        </gen:ReportedAttribute>
        <gen:ReportedAttribute id="ORGANISATION_UNIT">
          <com:Text xml:lang="en"/>
        </gen:ReportedAttribute>
        <gen:ReportedAttribute id="CONTACT_FUNCT">
          <com:Text xml:lang="en"/>
        </gen:ReportedAttribute>
        <gen:ReportedAttribute id="CONTACT_PHONE">
          <com:Text xml:lang="en"/>
        </gen:ReportedAttribute>
        <gen:ReportedAttribute id="CONTACT_MAIL">
          <com:Text xml:lang="en"/>
        </gen:ReportedAttribute>
        <gen:ReportedAttribute id="CONTACT_EMAIL">
          <com:Text xml:lang="en"/>
        </gen:ReportedAttribute>
        <gen:ReportedAttribute id="IND_DEF_CON_CLASS">
          <com:Text xml:lang="en"/>
        </gen:ReportedAttribute>
        <gen:ReportedAttribute id="STAT_CONC_DEF">
          <com:Text xml:lang="en"/>
        </gen:ReportedAttribute>
        <gen:ReportedAttribute id="UNIT_MEASURE">
          <com:Text xml:lang="en"/>
        </gen:ReportedAttribute>
        <gen:ReportedAttribute id="CLASS_SYSTEM">
          <com:Text xml:lang="en"/>
        </gen:ReportedAttribute>
        <gen:ReportedAttribute id="SRC_TYPE_COLL_METHOD">
          <com:Text xml:lang="en"/>
        </gen:ReportedAttribute>
        <gen:ReportedAttribute id="SOURCE_TYPE">
          <com:Text xml:lang="en"/>
        </gen:ReportedAttribute>
        <gen:ReportedAttribute id="COLL_METHOD">
          <com:Text xml:lang="en"/>
        </gen:ReportedAttribute>
        <gen:ReportedAttribute id="FREQ_COLL">
          <com:Text xml:lang="en"/>
        </gen:ReportedAttribute>
        <gen:ReportedAttribute id="REL_CAL_POLICY">
          <com:Text xml:lang="en"/>
        </gen:ReportedAttribute>
        <gen:ReportedAttribute id="DATA_SOURCE">
          <com:Text xml:lang="en"/>
        </gen:ReportedAttribute>
        <gen:ReportedAttribute id="COMPILING_ORG">
          <com:Text xml:lang="en"/>
        </gen:ReportedAttribute>
        <gen:ReportedAttribute id="INST_MANDATE">
          <com:Text xml:lang="en"/>
        </gen:ReportedAttribute>
        <gen:ReportedAttribute id="OTHER_METHOD">
          <com:Text xml:lang="en"/>
        </gen:ReportedAttribute>
        <gen:ReportedAttribute id="RATIONALE">
          <com:Text xml:lang="en"/>
        </gen:ReportedAttribute>
        <gen:ReportedAttribute id="REC_USE_LIM">
          <com:Text xml:lang="en"/>
        </gen:ReportedAttribute>
        <gen:ReportedAttribute id="DATA_COMP">
          <com:Text xml:lang="en"/>
        </gen:ReportedAttribute>
        <gen:ReportedAttribute id="DATA_VALIDATION">
          <com:Text xml:lang="en"/>
        </gen:ReportedAttribute>
        <gen:ReportedAttribute id="ADJUSTMENT">
          <com:Text xml:lang="en"/>
        </gen:ReportedAttribute>
        <gen:ReportedAttribute id="IMPUTATION">
          <com:Text xml:lang="en"/>
        </gen:ReportedAttribute>
        <gen:ReportedAttribute id="REG_AGG">
          <com:Text xml:lang="en"/>
        </gen:ReportedAttribute>
        <gen:ReportedAttribute id="DOC_METHOD">
          <com:Text xml:lang="en"/>
        </gen:ReportedAttribute>
        <gen:ReportedAttribute id="QUALITY_MGMNT">
          <com:Text xml:lang="en"/>
        </gen:ReportedAttribute>
        <gen:ReportedAttribute id="QUALITY_ASSURE">
          <com:Text xml:lang="en"/>
        </gen:ReportedAttribute>
        <gen:ReportedAttribute id="QUALITY_ASSMNT">
          <com:Text xml:lang="en"/>
        </gen:ReportedAttribute>
        <gen:ReportedAttribute id="COVERAGE">
          <com:Text xml:lang="en"/>
        </gen:ReportedAttribute>
        <gen:ReportedAttribute id="COMPARABILITY">
          <com:Text xml:lang="en"/>
        </gen:ReportedAttribute>
        <gen:ReportedAttribute id="OTHER_DOC">
          <com:Text xml:lang="en"/>
        </gen:ReportedAttribute>
      </gen:AttributeSet>
    </gen:Report>
  </mes:MetadataSet>
  <mes:MetadataSet structureRef="MDS1" setID="fc9df422-e03d-4735-9154-f9c1128b7e54">
    <com:Name xml:lang="en">SDG METADATA SET</com:Name>
    <gen:Report id="SDG_META_RPT">
      <gen:Target id="KEY_TARGET">
        <gen:ReferenceValue id="DIMENSION_DESCRIPTOR_VALUES_TARGET">
          <gen:DataKey>
            <com:KeyValue id="SERIES">
              <com:Value>SE_TOT_GPI</com:Value>
            </com:KeyValue>
            <com:KeyValue id="REPORTING_TYPE">
              <com:Value>N</com:Value>
            </com:KeyValue>
            <com:KeyValue id="REF_AREA">
              <com:Value>BI</com:Value>
            </com:KeyValue>
          </gen:DataKey>
        </gen:ReferenceValue>
        <gen:ReferenceValue id="Dataflow">
          <gen:ObjectReference>
            <URN>urn:sdmx:org.sdmx.infomodel.datastructure.Dataflow=IAEG-SDGs:DF_SDG_GLC(1.0)</URN>
          </gen:ObjectReference>
        </gen:ReferenceValue>
      </gen:Target>
      <gen:AttributeSet>
        <gen:ReportedAttribute id="SDG_INDICATOR_INFO">
          <com:Text xml:lang="en"/>
        </gen:ReportedAttribute>
        <gen:ReportedAttribute id="SDG_GOAL">
          <com:Text xml:lang="en"/>
        </gen:ReportedAttribute>
        <gen:ReportedAttribute id="SDG_TARGET">
          <com:Text xml:lang="en"/>
        </gen:ReportedAttribute>
        <gen:ReportedAttribute id="SDG_INDICATOR">
          <com:Text xml:lang="en"/>
        </gen:ReportedAttribute>
        <gen:ReportedAttribute id="SDG_SERIES_DESCR">
          <com:Text xml:lang="en"/>
        </gen:ReportedAttribute>
        <gen:ReportedAttribute id="META_LAST_UPDATE">
          <com:Text xml:lang="en"/>
        </gen:ReportedAttribute>
        <gen:ReportedAttribute id="SDG_RELATED_INDICATORS">
          <com:Text xml:lang="en"/>
        </gen:ReportedAttribute>
        <gen:ReportedAttribute id="SDG_CUSTODIAN_AGENCIES">
          <com:Text xml:lang="en"/>
        </gen:ReportedAttribute>
        <gen:ReportedAttribute id="CONTACT">
          <com:Text xml:lang="en"/>
        </gen:ReportedAttribute>
        <gen:ReportedAttribute id="CONTACT_ORGANISATION">
          <com:Text xml:lang="en"/>
        </gen:ReportedAttribute>
        <gen:ReportedAttribute id="CONTACT_NAME">
          <com:Text xml:lang="en"/>
        </gen:ReportedAttribute>
        <gen:ReportedAttribute id="ORGANISATION_UNIT">
          <com:Text xml:lang="en"/>
        </gen:ReportedAttribute>
        <gen:ReportedAttribute id="CONTACT_FUNCT">
          <com:Text xml:lang="en"/>
        </gen:ReportedAttribute>
        <gen:ReportedAttribute id="CONTACT_PHONE">
          <com:Text xml:lang="en"/>
        </gen:ReportedAttribute>
        <gen:ReportedAttribute id="CONTACT_MAIL">
          <com:Text xml:lang="en"/>
        </gen:ReportedAttribute>
        <gen:ReportedAttribute id="CONTACT_EMAIL">
          <com:Text xml:lang="en"/>
        </gen:ReportedAttribute>
        <gen:ReportedAttribute id="IND_DEF_CON_CLASS">
          <com:Text xml:lang="en"/>
        </gen:ReportedAttribute>
        <gen:ReportedAttribute id="STAT_CONC_DEF">
          <com:Text xml:lang="en"/>
        </gen:ReportedAttribute>
        <gen:ReportedAttribute id="UNIT_MEASURE">
          <com:Text xml:lang="en"/>
        </gen:ReportedAttribute>
        <gen:ReportedAttribute id="CLASS_SYSTEM">
          <com:Text xml:lang="en"/>
        </gen:ReportedAttribute>
        <gen:ReportedAttribute id="SRC_TYPE_COLL_METHOD">
          <com:Text xml:lang="en"/>
        </gen:ReportedAttribute>
        <gen:ReportedAttribute id="SOURCE_TYPE">
          <com:Text xml:lang="en"/>
        </gen:ReportedAttribute>
        <gen:ReportedAttribute id="COLL_METHOD">
          <com:Text xml:lang="en"/>
        </gen:ReportedAttribute>
        <gen:ReportedAttribute id="FREQ_COLL">
          <com:Text xml:lang="en"/>
        </gen:ReportedAttribute>
        <gen:ReportedAttribute id="REL_CAL_POLICY">
          <com:Text xml:lang="en"/>
        </gen:ReportedAttribute>
        <gen:ReportedAttribute id="DATA_SOURCE">
          <com:Text xml:lang="en"/>
        </gen:ReportedAttribute>
        <gen:ReportedAttribute id="COMPILING_ORG">
          <com:Text xml:lang="en"/>
        </gen:ReportedAttribute>
        <gen:ReportedAttribute id="INST_MANDATE">
          <com:Text xml:lang="en"/>
        </gen:ReportedAttribute>
        <gen:ReportedAttribute id="OTHER_METHOD">
          <com:Text xml:lang="en"/>
        </gen:ReportedAttribute>
        <gen:ReportedAttribute id="RATIONALE">
          <com:Text xml:lang="en"/>
        </gen:ReportedAttribute>
        <gen:ReportedAttribute id="REC_USE_LIM">
          <com:Text xml:lang="en"/>
        </gen:ReportedAttribute>
        <gen:ReportedAttribute id="DATA_COMP">
          <com:Text xml:lang="en"/>
        </gen:ReportedAttribute>
        <gen:ReportedAttribute id="DATA_VALIDATION">
          <com:Text xml:lang="en"/>
        </gen:ReportedAttribute>
        <gen:ReportedAttribute id="ADJUSTMENT">
          <com:Text xml:lang="en"/>
        </gen:ReportedAttribute>
        <gen:ReportedAttribute id="IMPUTATION">
          <com:Text xml:lang="en"/>
        </gen:ReportedAttribute>
        <gen:ReportedAttribute id="REG_AGG">
          <com:Text xml:lang="en"/>
        </gen:ReportedAttribute>
        <gen:ReportedAttribute id="DOC_METHOD">
          <com:Text xml:lang="en"/>
        </gen:ReportedAttribute>
        <gen:ReportedAttribute id="QUALITY_MGMNT">
          <com:Text xml:lang="en"/>
        </gen:ReportedAttribute>
        <gen:ReportedAttribute id="QUALITY_ASSURE">
          <com:Text xml:lang="en"/>
        </gen:ReportedAttribute>
        <gen:ReportedAttribute id="QUALITY_ASSMNT">
          <com:Text xml:lang="en"/>
        </gen:ReportedAttribute>
        <gen:ReportedAttribute id="COVERAGE">
          <com:Text xml:lang="en"/>
        </gen:ReportedAttribute>
        <gen:ReportedAttribute id="COMPARABILITY">
          <com:Text xml:lang="en"/>
        </gen:ReportedAttribute>
        <gen:ReportedAttribute id="OTHER_DOC">
          <com:Text xml:lang="en"/>
        </gen:ReportedAttribute>
      </gen:AttributeSet>
    </gen:Report>
  </mes:MetadataSet>
  <mes:MetadataSet structureRef="MDS1" setID="8687a1d2-2701-4f10-8d82-106ba7dba05c">
    <com:Name xml:lang="en">SDG METADATA SET</com:Name>
    <gen:Report id="SDG_META_RPT">
      <gen:Target id="KEY_TARGET">
        <gen:ReferenceValue id="DIMENSION_DESCRIPTOR_VALUES_TARGET">
          <gen:DataKey>
            <com:KeyValue id="SERIES">
              <com:Value>SE_TOT_SESPI</com:Value>
            </com:KeyValue>
            <com:KeyValue id="REPORTING_TYPE">
              <com:Value>N</com:Value>
            </com:KeyValue>
            <com:KeyValue id="REF_AREA">
              <com:Value>BI</com:Value>
            </com:KeyValue>
          </gen:DataKey>
        </gen:ReferenceValue>
        <gen:ReferenceValue id="Dataflow">
          <gen:ObjectReference>
            <URN>urn:sdmx:org.sdmx.infomodel.datastructure.Dataflow=IAEG-SDGs:DF_SDG_GLC(1.0)</URN>
          </gen:ObjectReference>
        </gen:ReferenceValue>
      </gen:Target>
      <gen:AttributeSet>
        <gen:ReportedAttribute id="SDG_INDICATOR_INFO">
          <com:Text xml:lang="en"/>
        </gen:ReportedAttribute>
        <gen:ReportedAttribute id="SDG_GOAL">
          <com:Text xml:lang="en"/>
        </gen:ReportedAttribute>
        <gen:ReportedAttribute id="SDG_TARGET">
          <com:Text xml:lang="en"/>
        </gen:ReportedAttribute>
        <gen:ReportedAttribute id="SDG_INDICATOR">
          <com:Text xml:lang="en"/>
        </gen:ReportedAttribute>
        <gen:ReportedAttribute id="SDG_SERIES_DESCR">
          <com:Text xml:lang="en"/>
        </gen:ReportedAttribute>
        <gen:ReportedAttribute id="META_LAST_UPDATE">
          <com:Text xml:lang="en"/>
        </gen:ReportedAttribute>
        <gen:ReportedAttribute id="SDG_RELATED_INDICATORS">
          <com:Text xml:lang="en"/>
        </gen:ReportedAttribute>
        <gen:ReportedAttribute id="SDG_CUSTODIAN_AGENCIES">
          <com:Text xml:lang="en"/>
        </gen:ReportedAttribute>
        <gen:ReportedAttribute id="CONTACT">
          <com:Text xml:lang="en"/>
        </gen:ReportedAttribute>
        <gen:ReportedAttribute id="CONTACT_ORGANISATION">
          <com:Text xml:lang="en"/>
        </gen:ReportedAttribute>
        <gen:ReportedAttribute id="CONTACT_NAME">
          <com:Text xml:lang="en"/>
        </gen:ReportedAttribute>
        <gen:ReportedAttribute id="ORGANISATION_UNIT">
          <com:Text xml:lang="en"/>
        </gen:ReportedAttribute>
        <gen:ReportedAttribute id="CONTACT_FUNCT">
          <com:Text xml:lang="en"/>
        </gen:ReportedAttribute>
        <gen:ReportedAttribute id="CONTACT_PHONE">
          <com:Text xml:lang="en"/>
        </gen:ReportedAttribute>
        <gen:ReportedAttribute id="CONTACT_MAIL">
          <com:Text xml:lang="en"/>
        </gen:ReportedAttribute>
        <gen:ReportedAttribute id="CONTACT_EMAIL">
          <com:Text xml:lang="en"/>
        </gen:ReportedAttribute>
        <gen:ReportedAttribute id="IND_DEF_CON_CLASS">
          <com:Text xml:lang="en"/>
        </gen:ReportedAttribute>
        <gen:ReportedAttribute id="STAT_CONC_DEF">
          <com:Text xml:lang="en"/>
        </gen:ReportedAttribute>
        <gen:ReportedAttribute id="UNIT_MEASURE">
          <com:Text xml:lang="en"/>
        </gen:ReportedAttribute>
        <gen:ReportedAttribute id="CLASS_SYSTEM">
          <com:Text xml:lang="en"/>
        </gen:ReportedAttribute>
        <gen:ReportedAttribute id="SRC_TYPE_COLL_METHOD">
          <com:Text xml:lang="en"/>
        </gen:ReportedAttribute>
        <gen:ReportedAttribute id="SOURCE_TYPE">
          <com:Text xml:lang="en"/>
        </gen:ReportedAttribute>
        <gen:ReportedAttribute id="COLL_METHOD">
          <com:Text xml:lang="en"/>
        </gen:ReportedAttribute>
        <gen:ReportedAttribute id="FREQ_COLL">
          <com:Text xml:lang="en"/>
        </gen:ReportedAttribute>
        <gen:ReportedAttribute id="REL_CAL_POLICY">
          <com:Text xml:lang="en"/>
        </gen:ReportedAttribute>
        <gen:ReportedAttribute id="DATA_SOURCE">
          <com:Text xml:lang="en"/>
        </gen:ReportedAttribute>
        <gen:ReportedAttribute id="COMPILING_ORG">
          <com:Text xml:lang="en"/>
        </gen:ReportedAttribute>
        <gen:ReportedAttribute id="INST_MANDATE">
          <com:Text xml:lang="en"/>
        </gen:ReportedAttribute>
        <gen:ReportedAttribute id="OTHER_METHOD">
          <com:Text xml:lang="en"/>
        </gen:ReportedAttribute>
        <gen:ReportedAttribute id="RATIONALE">
          <com:Text xml:lang="en"/>
        </gen:ReportedAttribute>
        <gen:ReportedAttribute id="REC_USE_LIM">
          <com:Text xml:lang="en"/>
        </gen:ReportedAttribute>
        <gen:ReportedAttribute id="DATA_COMP">
          <com:Text xml:lang="en"/>
        </gen:ReportedAttribute>
        <gen:ReportedAttribute id="DATA_VALIDATION">
          <com:Text xml:lang="en"/>
        </gen:ReportedAttribute>
        <gen:ReportedAttribute id="ADJUSTMENT">
          <com:Text xml:lang="en"/>
        </gen:ReportedAttribute>
        <gen:ReportedAttribute id="IMPUTATION">
          <com:Text xml:lang="en"/>
        </gen:ReportedAttribute>
        <gen:ReportedAttribute id="REG_AGG">
          <com:Text xml:lang="en"/>
        </gen:ReportedAttribute>
        <gen:ReportedAttribute id="DOC_METHOD">
          <com:Text xml:lang="en"/>
        </gen:ReportedAttribute>
        <gen:ReportedAttribute id="QUALITY_MGMNT">
          <com:Text xml:lang="en"/>
        </gen:ReportedAttribute>
        <gen:ReportedAttribute id="QUALITY_ASSURE">
          <com:Text xml:lang="en"/>
        </gen:ReportedAttribute>
        <gen:ReportedAttribute id="QUALITY_ASSMNT">
          <com:Text xml:lang="en"/>
        </gen:ReportedAttribute>
        <gen:ReportedAttribute id="COVERAGE">
          <com:Text xml:lang="en"/>
        </gen:ReportedAttribute>
        <gen:ReportedAttribute id="COMPARABILITY">
          <com:Text xml:lang="en"/>
        </gen:ReportedAttribute>
        <gen:ReportedAttribute id="OTHER_DOC">
          <com:Text xml:lang="en"/>
        </gen:ReportedAttribute>
      </gen:AttributeSet>
    </gen:Report>
  </mes:MetadataSet>
  <mes:MetadataSet structureRef="MDS1" setID="6a0527ce-f593-4bdb-88a5-0ac117e4dda3">
    <com:Name xml:lang="en">SDG METADATA SET</com:Name>
    <gen:Report id="SDG_META_RPT">
      <gen:Target id="KEY_TARGET">
        <gen:ReferenceValue id="DIMENSION_DESCRIPTOR_VALUES_TARGET">
          <gen:DataKey>
            <com:KeyValue id="SERIES">
              <com:Value>SE_TOT_RUPI</com:Value>
            </com:KeyValue>
            <com:KeyValue id="REPORTING_TYPE">
              <com:Value>N</com:Value>
            </com:KeyValue>
            <com:KeyValue id="REF_AREA">
              <com:Value>BI</com:Value>
            </com:KeyValue>
          </gen:DataKey>
        </gen:ReferenceValue>
        <gen:ReferenceValue id="Dataflow">
          <gen:ObjectReference>
            <URN>urn:sdmx:org.sdmx.infomodel.datastructure.Dataflow=IAEG-SDGs:DF_SDG_GLC(1.0)</URN>
          </gen:ObjectReference>
        </gen:ReferenceValue>
      </gen:Target>
      <gen:AttributeSet>
        <gen:ReportedAttribute id="SDG_INDICATOR_INFO">
          <com:Text xml:lang="en"/>
        </gen:ReportedAttribute>
        <gen:ReportedAttribute id="SDG_GOAL">
          <com:Text xml:lang="en"/>
        </gen:ReportedAttribute>
        <gen:ReportedAttribute id="SDG_TARGET">
          <com:Text xml:lang="en"/>
        </gen:ReportedAttribute>
        <gen:ReportedAttribute id="SDG_INDICATOR">
          <com:Text xml:lang="en"/>
        </gen:ReportedAttribute>
        <gen:ReportedAttribute id="SDG_SERIES_DESCR">
          <com:Text xml:lang="en"/>
        </gen:ReportedAttribute>
        <gen:ReportedAttribute id="META_LAST_UPDATE">
          <com:Text xml:lang="en"/>
        </gen:ReportedAttribute>
        <gen:ReportedAttribute id="SDG_RELATED_INDICATORS">
          <com:Text xml:lang="en"/>
        </gen:ReportedAttribute>
        <gen:ReportedAttribute id="SDG_CUSTODIAN_AGENCIES">
          <com:Text xml:lang="en"/>
        </gen:ReportedAttribute>
        <gen:ReportedAttribute id="CONTACT">
          <com:Text xml:lang="en"/>
        </gen:ReportedAttribute>
        <gen:ReportedAttribute id="CONTACT_ORGANISATION">
          <com:Text xml:lang="en"/>
        </gen:ReportedAttribute>
        <gen:ReportedAttribute id="CONTACT_NAME">
          <com:Text xml:lang="en"/>
        </gen:ReportedAttribute>
        <gen:ReportedAttribute id="ORGANISATION_UNIT">
          <com:Text xml:lang="en"/>
        </gen:ReportedAttribute>
        <gen:ReportedAttribute id="CONTACT_FUNCT">
          <com:Text xml:lang="en"/>
        </gen:ReportedAttribute>
        <gen:ReportedAttribute id="CONTACT_PHONE">
          <com:Text xml:lang="en"/>
        </gen:ReportedAttribute>
        <gen:ReportedAttribute id="CONTACT_MAIL">
          <com:Text xml:lang="en"/>
        </gen:ReportedAttribute>
        <gen:ReportedAttribute id="CONTACT_EMAIL">
          <com:Text xml:lang="en"/>
        </gen:ReportedAttribute>
        <gen:ReportedAttribute id="IND_DEF_CON_CLASS">
          <com:Text xml:lang="en"/>
        </gen:ReportedAttribute>
        <gen:ReportedAttribute id="STAT_CONC_DEF">
          <com:Text xml:lang="en"/>
        </gen:ReportedAttribute>
        <gen:ReportedAttribute id="UNIT_MEASURE">
          <com:Text xml:lang="en"/>
        </gen:ReportedAttribute>
        <gen:ReportedAttribute id="CLASS_SYSTEM">
          <com:Text xml:lang="en"/>
        </gen:ReportedAttribute>
        <gen:ReportedAttribute id="SRC_TYPE_COLL_METHOD">
          <com:Text xml:lang="en"/>
        </gen:ReportedAttribute>
        <gen:ReportedAttribute id="SOURCE_TYPE">
          <com:Text xml:lang="en"/>
        </gen:ReportedAttribute>
        <gen:ReportedAttribute id="COLL_METHOD">
          <com:Text xml:lang="en"/>
        </gen:ReportedAttribute>
        <gen:ReportedAttribute id="FREQ_COLL">
          <com:Text xml:lang="en"/>
        </gen:ReportedAttribute>
        <gen:ReportedAttribute id="REL_CAL_POLICY">
          <com:Text xml:lang="en"/>
        </gen:ReportedAttribute>
        <gen:ReportedAttribute id="DATA_SOURCE">
          <com:Text xml:lang="en"/>
        </gen:ReportedAttribute>
        <gen:ReportedAttribute id="COMPILING_ORG">
          <com:Text xml:lang="en"/>
        </gen:ReportedAttribute>
        <gen:ReportedAttribute id="INST_MANDATE">
          <com:Text xml:lang="en"/>
        </gen:ReportedAttribute>
        <gen:ReportedAttribute id="OTHER_METHOD">
          <com:Text xml:lang="en"/>
        </gen:ReportedAttribute>
        <gen:ReportedAttribute id="RATIONALE">
          <com:Text xml:lang="en"/>
        </gen:ReportedAttribute>
        <gen:ReportedAttribute id="REC_USE_LIM">
          <com:Text xml:lang="en"/>
        </gen:ReportedAttribute>
        <gen:ReportedAttribute id="DATA_COMP">
          <com:Text xml:lang="en"/>
        </gen:ReportedAttribute>
        <gen:ReportedAttribute id="DATA_VALIDATION">
          <com:Text xml:lang="en"/>
        </gen:ReportedAttribute>
        <gen:ReportedAttribute id="ADJUSTMENT">
          <com:Text xml:lang="en"/>
        </gen:ReportedAttribute>
        <gen:ReportedAttribute id="IMPUTATION">
          <com:Text xml:lang="en"/>
        </gen:ReportedAttribute>
        <gen:ReportedAttribute id="REG_AGG">
          <com:Text xml:lang="en"/>
        </gen:ReportedAttribute>
        <gen:ReportedAttribute id="DOC_METHOD">
          <com:Text xml:lang="en"/>
        </gen:ReportedAttribute>
        <gen:ReportedAttribute id="QUALITY_MGMNT">
          <com:Text xml:lang="en"/>
        </gen:ReportedAttribute>
        <gen:ReportedAttribute id="QUALITY_ASSURE">
          <com:Text xml:lang="en"/>
        </gen:ReportedAttribute>
        <gen:ReportedAttribute id="QUALITY_ASSMNT">
          <com:Text xml:lang="en"/>
        </gen:ReportedAttribute>
        <gen:ReportedAttribute id="COVERAGE">
          <com:Text xml:lang="en"/>
        </gen:ReportedAttribute>
        <gen:ReportedAttribute id="COMPARABILITY">
          <com:Text xml:lang="en"/>
        </gen:ReportedAttribute>
        <gen:ReportedAttribute id="OTHER_DOC">
          <com:Text xml:lang="en"/>
        </gen:ReportedAttribute>
      </gen:AttributeSet>
    </gen:Report>
  </mes:MetadataSet>
  <mes:MetadataSet structureRef="MDS1" setID="f8416df8-ef41-496c-8784-bd71fb7b8f72">
    <com:Name xml:lang="en">SDG METADATA SET</com:Name>
    <gen:Report id="SDG_META_RPT">
      <gen:Target id="KEY_TARGET">
        <gen:ReferenceValue id="DIMENSION_DESCRIPTOR_VALUES_TARGET">
          <gen:DataKey>
            <com:KeyValue id="SERIES">
              <com:Value>SE_GPI_TCAQ</com:Value>
            </com:KeyValue>
            <com:KeyValue id="REPORTING_TYPE">
              <com:Value>N</com:Value>
            </com:KeyValue>
            <com:KeyValue id="REF_AREA">
              <com:Value>BI</com:Value>
            </com:KeyValue>
          </gen:DataKey>
        </gen:ReferenceValue>
        <gen:ReferenceValue id="Dataflow">
          <gen:ObjectReference>
            <URN>urn:sdmx:org.sdmx.infomodel.datastructure.Dataflow=IAEG-SDGs:DF_SDG_GLC(1.0)</URN>
          </gen:ObjectReference>
        </gen:ReferenceValue>
      </gen:Target>
      <gen:AttributeSet>
        <gen:ReportedAttribute id="SDG_INDICATOR_INFO">
          <com:Text xml:lang="en"/>
        </gen:ReportedAttribute>
        <gen:ReportedAttribute id="SDG_GOAL">
          <com:Text xml:lang="en"/>
        </gen:ReportedAttribute>
        <gen:ReportedAttribute id="SDG_TARGET">
          <com:Text xml:lang="en"/>
        </gen:ReportedAttribute>
        <gen:ReportedAttribute id="SDG_INDICATOR">
          <com:Text xml:lang="en"/>
        </gen:ReportedAttribute>
        <gen:ReportedAttribute id="SDG_SERIES_DESCR">
          <com:Text xml:lang="en"/>
        </gen:ReportedAttribute>
        <gen:ReportedAttribute id="META_LAST_UPDATE">
          <com:Text xml:lang="en"/>
        </gen:ReportedAttribute>
        <gen:ReportedAttribute id="SDG_RELATED_INDICATORS">
          <com:Text xml:lang="en"/>
        </gen:ReportedAttribute>
        <gen:ReportedAttribute id="SDG_CUSTODIAN_AGENCIES">
          <com:Text xml:lang="en"/>
        </gen:ReportedAttribute>
        <gen:ReportedAttribute id="CONTACT">
          <com:Text xml:lang="en"/>
        </gen:ReportedAttribute>
        <gen:ReportedAttribute id="CONTACT_ORGANISATION">
          <com:Text xml:lang="en"/>
        </gen:ReportedAttribute>
        <gen:ReportedAttribute id="CONTACT_NAME">
          <com:Text xml:lang="en"/>
        </gen:ReportedAttribute>
        <gen:ReportedAttribute id="ORGANISATION_UNIT">
          <com:Text xml:lang="en"/>
        </gen:ReportedAttribute>
        <gen:ReportedAttribute id="CONTACT_FUNCT">
          <com:Text xml:lang="en"/>
        </gen:ReportedAttribute>
        <gen:ReportedAttribute id="CONTACT_PHONE">
          <com:Text xml:lang="en"/>
        </gen:ReportedAttribute>
        <gen:ReportedAttribute id="CONTACT_MAIL">
          <com:Text xml:lang="en"/>
        </gen:ReportedAttribute>
        <gen:ReportedAttribute id="CONTACT_EMAIL">
          <com:Text xml:lang="en"/>
        </gen:ReportedAttribute>
        <gen:ReportedAttribute id="IND_DEF_CON_CLASS">
          <com:Text xml:lang="en"/>
        </gen:ReportedAttribute>
        <gen:ReportedAttribute id="STAT_CONC_DEF">
          <com:Text xml:lang="en"/>
        </gen:ReportedAttribute>
        <gen:ReportedAttribute id="UNIT_MEASURE">
          <com:Text xml:lang="en"/>
        </gen:ReportedAttribute>
        <gen:ReportedAttribute id="CLASS_SYSTEM">
          <com:Text xml:lang="en"/>
        </gen:ReportedAttribute>
        <gen:ReportedAttribute id="SRC_TYPE_COLL_METHOD">
          <com:Text xml:lang="en"/>
        </gen:ReportedAttribute>
        <gen:ReportedAttribute id="SOURCE_TYPE">
          <com:Text xml:lang="en"/>
        </gen:ReportedAttribute>
        <gen:ReportedAttribute id="COLL_METHOD">
          <com:Text xml:lang="en"/>
        </gen:ReportedAttribute>
        <gen:ReportedAttribute id="FREQ_COLL">
          <com:Text xml:lang="en"/>
        </gen:ReportedAttribute>
        <gen:ReportedAttribute id="REL_CAL_POLICY">
          <com:Text xml:lang="en"/>
        </gen:ReportedAttribute>
        <gen:ReportedAttribute id="DATA_SOURCE">
          <com:Text xml:lang="en"/>
        </gen:ReportedAttribute>
        <gen:ReportedAttribute id="COMPILING_ORG">
          <com:Text xml:lang="en"/>
        </gen:ReportedAttribute>
        <gen:ReportedAttribute id="INST_MANDATE">
          <com:Text xml:lang="en"/>
        </gen:ReportedAttribute>
        <gen:ReportedAttribute id="OTHER_METHOD">
          <com:Text xml:lang="en"/>
        </gen:ReportedAttribute>
        <gen:ReportedAttribute id="RATIONALE">
          <com:Text xml:lang="en"/>
        </gen:ReportedAttribute>
        <gen:ReportedAttribute id="REC_USE_LIM">
          <com:Text xml:lang="en"/>
        </gen:ReportedAttribute>
        <gen:ReportedAttribute id="DATA_COMP">
          <com:Text xml:lang="en"/>
        </gen:ReportedAttribute>
        <gen:ReportedAttribute id="DATA_VALIDATION">
          <com:Text xml:lang="en"/>
        </gen:ReportedAttribute>
        <gen:ReportedAttribute id="ADJUSTMENT">
          <com:Text xml:lang="en"/>
        </gen:ReportedAttribute>
        <gen:ReportedAttribute id="IMPUTATION">
          <com:Text xml:lang="en"/>
        </gen:ReportedAttribute>
        <gen:ReportedAttribute id="REG_AGG">
          <com:Text xml:lang="en"/>
        </gen:ReportedAttribute>
        <gen:ReportedAttribute id="DOC_METHOD">
          <com:Text xml:lang="en"/>
        </gen:ReportedAttribute>
        <gen:ReportedAttribute id="QUALITY_MGMNT">
          <com:Text xml:lang="en"/>
        </gen:ReportedAttribute>
        <gen:ReportedAttribute id="QUALITY_ASSURE">
          <com:Text xml:lang="en"/>
        </gen:ReportedAttribute>
        <gen:ReportedAttribute id="QUALITY_ASSMNT">
          <com:Text xml:lang="en"/>
        </gen:ReportedAttribute>
        <gen:ReportedAttribute id="COVERAGE">
          <com:Text xml:lang="en"/>
        </gen:ReportedAttribute>
        <gen:ReportedAttribute id="COMPARABILITY">
          <com:Text xml:lang="en"/>
        </gen:ReportedAttribute>
        <gen:ReportedAttribute id="OTHER_DOC">
          <com:Text xml:lang="en"/>
        </gen:ReportedAttribute>
      </gen:AttributeSet>
    </gen:Report>
  </mes:MetadataSet>
  <mes:MetadataSet structureRef="MDS1" setID="b4932039-c5e5-499e-9b06-39027f095dbf">
    <com:Name xml:lang="en">SDG METADATA SET</com:Name>
    <gen:Report id="SDG_META_RPT">
      <gen:Target id="KEY_TARGET">
        <gen:ReferenceValue id="DIMENSION_DESCRIPTOR_VALUES_TARGET">
          <gen:DataKey>
            <com:KeyValue id="SERIES">
              <com:Value>SE_GPI_PTNPRE</com:Value>
            </com:KeyValue>
            <com:KeyValue id="REPORTING_TYPE">
              <com:Value>N</com:Value>
            </com:KeyValue>
            <com:KeyValue id="REF_AREA">
              <com:Value>BI</com:Value>
            </com:KeyValue>
          </gen:DataKey>
        </gen:ReferenceValue>
        <gen:ReferenceValue id="Dataflow">
          <gen:ObjectReference>
            <URN>urn:sdmx:org.sdmx.infomodel.datastructure.Dataflow=IAEG-SDGs:DF_SDG_GLC(1.0)</URN>
          </gen:ObjectReference>
        </gen:ReferenceValue>
      </gen:Target>
      <gen:AttributeSet>
        <gen:ReportedAttribute id="SDG_INDICATOR_INFO">
          <com:Text xml:lang="en"/>
        </gen:ReportedAttribute>
        <gen:ReportedAttribute id="SDG_GOAL">
          <com:Text xml:lang="en"/>
        </gen:ReportedAttribute>
        <gen:ReportedAttribute id="SDG_TARGET">
          <com:Text xml:lang="en"/>
        </gen:ReportedAttribute>
        <gen:ReportedAttribute id="SDG_INDICATOR">
          <com:Text xml:lang="en"/>
        </gen:ReportedAttribute>
        <gen:ReportedAttribute id="SDG_SERIES_DESCR">
          <com:Text xml:lang="en"/>
        </gen:ReportedAttribute>
        <gen:ReportedAttribute id="META_LAST_UPDATE">
          <com:Text xml:lang="en"/>
        </gen:ReportedAttribute>
        <gen:ReportedAttribute id="SDG_RELATED_INDICATORS">
          <com:Text xml:lang="en"/>
        </gen:ReportedAttribute>
        <gen:ReportedAttribute id="SDG_CUSTODIAN_AGENCIES">
          <com:Text xml:lang="en"/>
        </gen:ReportedAttribute>
        <gen:ReportedAttribute id="CONTACT">
          <com:Text xml:lang="en"/>
        </gen:ReportedAttribute>
        <gen:ReportedAttribute id="CONTACT_ORGANISATION">
          <com:Text xml:lang="en"/>
        </gen:ReportedAttribute>
        <gen:ReportedAttribute id="CONTACT_NAME">
          <com:Text xml:lang="en"/>
        </gen:ReportedAttribute>
        <gen:ReportedAttribute id="ORGANISATION_UNIT">
          <com:Text xml:lang="en"/>
        </gen:ReportedAttribute>
        <gen:ReportedAttribute id="CONTACT_FUNCT">
          <com:Text xml:lang="en"/>
        </gen:ReportedAttribute>
        <gen:ReportedAttribute id="CONTACT_PHONE">
          <com:Text xml:lang="en"/>
        </gen:ReportedAttribute>
        <gen:ReportedAttribute id="CONTACT_MAIL">
          <com:Text xml:lang="en"/>
        </gen:ReportedAttribute>
        <gen:ReportedAttribute id="CONTACT_EMAIL">
          <com:Text xml:lang="en"/>
        </gen:ReportedAttribute>
        <gen:ReportedAttribute id="IND_DEF_CON_CLASS">
          <com:Text xml:lang="en"/>
        </gen:ReportedAttribute>
        <gen:ReportedAttribute id="STAT_CONC_DEF">
          <com:Text xml:lang="en"/>
        </gen:ReportedAttribute>
        <gen:ReportedAttribute id="UNIT_MEASURE">
          <com:Text xml:lang="en"/>
        </gen:ReportedAttribute>
        <gen:ReportedAttribute id="CLASS_SYSTEM">
          <com:Text xml:lang="en"/>
        </gen:ReportedAttribute>
        <gen:ReportedAttribute id="SRC_TYPE_COLL_METHOD">
          <com:Text xml:lang="en"/>
        </gen:ReportedAttribute>
        <gen:ReportedAttribute id="SOURCE_TYPE">
          <com:Text xml:lang="en"/>
        </gen:ReportedAttribute>
        <gen:ReportedAttribute id="COLL_METHOD">
          <com:Text xml:lang="en"/>
        </gen:ReportedAttribute>
        <gen:ReportedAttribute id="FREQ_COLL">
          <com:Text xml:lang="en"/>
        </gen:ReportedAttribute>
        <gen:ReportedAttribute id="REL_CAL_POLICY">
          <com:Text xml:lang="en"/>
        </gen:ReportedAttribute>
        <gen:ReportedAttribute id="DATA_SOURCE">
          <com:Text xml:lang="en"/>
        </gen:ReportedAttribute>
        <gen:ReportedAttribute id="COMPILING_ORG">
          <com:Text xml:lang="en"/>
        </gen:ReportedAttribute>
        <gen:ReportedAttribute id="INST_MANDATE">
          <com:Text xml:lang="en"/>
        </gen:ReportedAttribute>
        <gen:ReportedAttribute id="OTHER_METHOD">
          <com:Text xml:lang="en"/>
        </gen:ReportedAttribute>
        <gen:ReportedAttribute id="RATIONALE">
          <com:Text xml:lang="en"/>
        </gen:ReportedAttribute>
        <gen:ReportedAttribute id="REC_USE_LIM">
          <com:Text xml:lang="en"/>
        </gen:ReportedAttribute>
        <gen:ReportedAttribute id="DATA_COMP">
          <com:Text xml:lang="en"/>
        </gen:ReportedAttribute>
        <gen:ReportedAttribute id="DATA_VALIDATION">
          <com:Text xml:lang="en"/>
        </gen:ReportedAttribute>
        <gen:ReportedAttribute id="ADJUSTMENT">
          <com:Text xml:lang="en"/>
        </gen:ReportedAttribute>
        <gen:ReportedAttribute id="IMPUTATION">
          <com:Text xml:lang="en"/>
        </gen:ReportedAttribute>
        <gen:ReportedAttribute id="REG_AGG">
          <com:Text xml:lang="en"/>
        </gen:ReportedAttribute>
        <gen:ReportedAttribute id="DOC_METHOD">
          <com:Text xml:lang="en"/>
        </gen:ReportedAttribute>
        <gen:ReportedAttribute id="QUALITY_MGMNT">
          <com:Text xml:lang="en"/>
        </gen:ReportedAttribute>
        <gen:ReportedAttribute id="QUALITY_ASSURE">
          <com:Text xml:lang="en"/>
        </gen:ReportedAttribute>
        <gen:ReportedAttribute id="QUALITY_ASSMNT">
          <com:Text xml:lang="en"/>
        </gen:ReportedAttribute>
        <gen:ReportedAttribute id="COVERAGE">
          <com:Text xml:lang="en"/>
        </gen:ReportedAttribute>
        <gen:ReportedAttribute id="COMPARABILITY">
          <com:Text xml:lang="en"/>
        </gen:ReportedAttribute>
        <gen:ReportedAttribute id="OTHER_DOC">
          <com:Text xml:lang="en"/>
        </gen:ReportedAttribute>
      </gen:AttributeSet>
    </gen:Report>
  </mes:MetadataSet>
  <mes:MetadataSet structureRef="MDS1" setID="862bfe35-b147-4f22-98c1-68e8eafdb54d">
    <com:Name xml:lang="en">SDG METADATA SET</com:Name>
    <gen:Report id="SDG_META_RPT">
      <gen:Target id="KEY_TARGET">
        <gen:ReferenceValue id="DIMENSION_DESCRIPTOR_VALUES_TARGET">
          <gen:DataKey>
            <com:KeyValue id="SERIES">
              <com:Value>SE_AGP_CPRA</com:Value>
            </com:KeyValue>
            <com:KeyValue id="REPORTING_TYPE">
              <com:Value>N</com:Value>
            </com:KeyValue>
            <com:KeyValue id="REF_AREA">
              <com:Value>BI</com:Value>
            </com:KeyValue>
          </gen:DataKey>
        </gen:ReferenceValue>
        <gen:ReferenceValue id="Dataflow">
          <gen:ObjectReference>
            <URN>urn:sdmx:org.sdmx.infomodel.datastructure.Dataflow=IAEG-SDGs:DF_SDG_GLC(1.0)</URN>
          </gen:ObjectReference>
        </gen:ReferenceValue>
      </gen:Target>
      <gen:AttributeSet>
        <gen:ReportedAttribute id="SDG_INDICATOR_INFO">
          <com:Text xml:lang="en"/>
        </gen:ReportedAttribute>
        <gen:ReportedAttribute id="SDG_GOAL">
          <com:Text xml:lang="en"/>
        </gen:ReportedAttribute>
        <gen:ReportedAttribute id="SDG_TARGET">
          <com:Text xml:lang="en"/>
        </gen:ReportedAttribute>
        <gen:ReportedAttribute id="SDG_INDICATOR">
          <com:Text xml:lang="en"/>
        </gen:ReportedAttribute>
        <gen:ReportedAttribute id="SDG_SERIES_DESCR">
          <com:Text xml:lang="en"/>
        </gen:ReportedAttribute>
        <gen:ReportedAttribute id="META_LAST_UPDATE">
          <com:Text xml:lang="en"/>
        </gen:ReportedAttribute>
        <gen:ReportedAttribute id="SDG_RELATED_INDICATORS">
          <com:Text xml:lang="en"/>
        </gen:ReportedAttribute>
        <gen:ReportedAttribute id="SDG_CUSTODIAN_AGENCIES">
          <com:Text xml:lang="en"/>
        </gen:ReportedAttribute>
        <gen:ReportedAttribute id="CONTACT">
          <com:Text xml:lang="en"/>
        </gen:ReportedAttribute>
        <gen:ReportedAttribute id="CONTACT_ORGANISATION">
          <com:Text xml:lang="en"/>
        </gen:ReportedAttribute>
        <gen:ReportedAttribute id="CONTACT_NAME">
          <com:Text xml:lang="en"/>
        </gen:ReportedAttribute>
        <gen:ReportedAttribute id="ORGANISATION_UNIT">
          <com:Text xml:lang="en"/>
        </gen:ReportedAttribute>
        <gen:ReportedAttribute id="CONTACT_FUNCT">
          <com:Text xml:lang="en"/>
        </gen:ReportedAttribute>
        <gen:ReportedAttribute id="CONTACT_PHONE">
          <com:Text xml:lang="en"/>
        </gen:ReportedAttribute>
        <gen:ReportedAttribute id="CONTACT_MAIL">
          <com:Text xml:lang="en"/>
        </gen:ReportedAttribute>
        <gen:ReportedAttribute id="CONTACT_EMAIL">
          <com:Text xml:lang="en"/>
        </gen:ReportedAttribute>
        <gen:ReportedAttribute id="IND_DEF_CON_CLASS">
          <com:Text xml:lang="en"/>
        </gen:ReportedAttribute>
        <gen:ReportedAttribute id="STAT_CONC_DEF">
          <com:Text xml:lang="en"/>
        </gen:ReportedAttribute>
        <gen:ReportedAttribute id="UNIT_MEASURE">
          <com:Text xml:lang="en"/>
        </gen:ReportedAttribute>
        <gen:ReportedAttribute id="CLASS_SYSTEM">
          <com:Text xml:lang="en"/>
        </gen:ReportedAttribute>
        <gen:ReportedAttribute id="SRC_TYPE_COLL_METHOD">
          <com:Text xml:lang="en"/>
        </gen:ReportedAttribute>
        <gen:ReportedAttribute id="SOURCE_TYPE">
          <com:Text xml:lang="en"/>
        </gen:ReportedAttribute>
        <gen:ReportedAttribute id="COLL_METHOD">
          <com:Text xml:lang="en"/>
        </gen:ReportedAttribute>
        <gen:ReportedAttribute id="FREQ_COLL">
          <com:Text xml:lang="en"/>
        </gen:ReportedAttribute>
        <gen:ReportedAttribute id="REL_CAL_POLICY">
          <com:Text xml:lang="en"/>
        </gen:ReportedAttribute>
        <gen:ReportedAttribute id="DATA_SOURCE">
          <com:Text xml:lang="en"/>
        </gen:ReportedAttribute>
        <gen:ReportedAttribute id="COMPILING_ORG">
          <com:Text xml:lang="en"/>
        </gen:ReportedAttribute>
        <gen:ReportedAttribute id="INST_MANDATE">
          <com:Text xml:lang="en"/>
        </gen:ReportedAttribute>
        <gen:ReportedAttribute id="OTHER_METHOD">
          <com:Text xml:lang="en"/>
        </gen:ReportedAttribute>
        <gen:ReportedAttribute id="RATIONALE">
          <com:Text xml:lang="en"/>
        </gen:ReportedAttribute>
        <gen:ReportedAttribute id="REC_USE_LIM">
          <com:Text xml:lang="en"/>
        </gen:ReportedAttribute>
        <gen:ReportedAttribute id="DATA_COMP">
          <com:Text xml:lang="en"/>
        </gen:ReportedAttribute>
        <gen:ReportedAttribute id="DATA_VALIDATION">
          <com:Text xml:lang="en"/>
        </gen:ReportedAttribute>
        <gen:ReportedAttribute id="ADJUSTMENT">
          <com:Text xml:lang="en"/>
        </gen:ReportedAttribute>
        <gen:ReportedAttribute id="IMPUTATION">
          <com:Text xml:lang="en"/>
        </gen:ReportedAttribute>
        <gen:ReportedAttribute id="REG_AGG">
          <com:Text xml:lang="en"/>
        </gen:ReportedAttribute>
        <gen:ReportedAttribute id="DOC_METHOD">
          <com:Text xml:lang="en"/>
        </gen:ReportedAttribute>
        <gen:ReportedAttribute id="QUALITY_MGMNT">
          <com:Text xml:lang="en"/>
        </gen:ReportedAttribute>
        <gen:ReportedAttribute id="QUALITY_ASSURE">
          <com:Text xml:lang="en"/>
        </gen:ReportedAttribute>
        <gen:ReportedAttribute id="QUALITY_ASSMNT">
          <com:Text xml:lang="en"/>
        </gen:ReportedAttribute>
        <gen:ReportedAttribute id="COVERAGE">
          <com:Text xml:lang="en"/>
        </gen:ReportedAttribute>
        <gen:ReportedAttribute id="COMPARABILITY">
          <com:Text xml:lang="en"/>
        </gen:ReportedAttribute>
        <gen:ReportedAttribute id="OTHER_DOC">
          <com:Text xml:lang="en"/>
        </gen:ReportedAttribute>
      </gen:AttributeSet>
    </gen:Report>
  </mes:MetadataSet>
  <mes:MetadataSet structureRef="MDS1" setID="50c3cfc3-dc05-49c1-b447-f239f0a6b832">
    <com:Name xml:lang="en">SDG METADATA SET</com:Name>
    <gen:Report id="SDG_META_RPT">
      <gen:Target id="KEY_TARGET">
        <gen:ReferenceValue id="DIMENSION_DESCRIPTOR_VALUES_TARGET">
          <gen:DataKey>
            <com:KeyValue id="SERIES">
              <com:Value>SE_ALP_CPLR</com:Value>
            </com:KeyValue>
            <com:KeyValue id="REPORTING_TYPE">
              <com:Value>N</com:Value>
            </com:KeyValue>
            <com:KeyValue id="REF_AREA">
              <com:Value>BI</com:Value>
            </com:KeyValue>
          </gen:DataKey>
        </gen:ReferenceValue>
        <gen:ReferenceValue id="Dataflow">
          <gen:ObjectReference>
            <URN>urn:sdmx:org.sdmx.infomodel.datastructure.Dataflow=IAEG-SDGs:DF_SDG_GLC(1.0)</URN>
          </gen:ObjectReference>
        </gen:ReferenceValue>
      </gen:Target>
      <gen:AttributeSet>
        <gen:ReportedAttribute id="SDG_INDICATOR_INFO">
          <com:Text xml:lang="en"/>
        </gen:ReportedAttribute>
        <gen:ReportedAttribute id="SDG_GOAL">
          <com:Text xml:lang="en"/>
        </gen:ReportedAttribute>
        <gen:ReportedAttribute id="SDG_TARGET">
          <com:Text xml:lang="en"/>
        </gen:ReportedAttribute>
        <gen:ReportedAttribute id="SDG_INDICATOR">
          <com:Text xml:lang="en"/>
        </gen:ReportedAttribute>
        <gen:ReportedAttribute id="SDG_SERIES_DESCR">
          <com:Text xml:lang="en"/>
        </gen:ReportedAttribute>
        <gen:ReportedAttribute id="META_LAST_UPDATE">
          <com:Text xml:lang="en"/>
        </gen:ReportedAttribute>
        <gen:ReportedAttribute id="SDG_RELATED_INDICATORS">
          <com:Text xml:lang="en"/>
        </gen:ReportedAttribute>
        <gen:ReportedAttribute id="SDG_CUSTODIAN_AGENCIES">
          <com:Text xml:lang="en"/>
        </gen:ReportedAttribute>
        <gen:ReportedAttribute id="CONTACT">
          <com:Text xml:lang="en"/>
        </gen:ReportedAttribute>
        <gen:ReportedAttribute id="CONTACT_ORGANISATION">
          <com:Text xml:lang="en"/>
        </gen:ReportedAttribute>
        <gen:ReportedAttribute id="CONTACT_NAME">
          <com:Text xml:lang="en"/>
        </gen:ReportedAttribute>
        <gen:ReportedAttribute id="ORGANISATION_UNIT">
          <com:Text xml:lang="en"/>
        </gen:ReportedAttribute>
        <gen:ReportedAttribute id="CONTACT_FUNCT">
          <com:Text xml:lang="en"/>
        </gen:ReportedAttribute>
        <gen:ReportedAttribute id="CONTACT_PHONE">
          <com:Text xml:lang="en"/>
        </gen:ReportedAttribute>
        <gen:ReportedAttribute id="CONTACT_MAIL">
          <com:Text xml:lang="en"/>
        </gen:ReportedAttribute>
        <gen:ReportedAttribute id="CONTACT_EMAIL">
          <com:Text xml:lang="en"/>
        </gen:ReportedAttribute>
        <gen:ReportedAttribute id="IND_DEF_CON_CLASS">
          <com:Text xml:lang="en"/>
        </gen:ReportedAttribute>
        <gen:ReportedAttribute id="STAT_CONC_DEF">
          <com:Text xml:lang="en"/>
        </gen:ReportedAttribute>
        <gen:ReportedAttribute id="UNIT_MEASURE">
          <com:Text xml:lang="en"/>
        </gen:ReportedAttribute>
        <gen:ReportedAttribute id="CLASS_SYSTEM">
          <com:Text xml:lang="en"/>
        </gen:ReportedAttribute>
        <gen:ReportedAttribute id="SRC_TYPE_COLL_METHOD">
          <com:Text xml:lang="en"/>
        </gen:ReportedAttribute>
        <gen:ReportedAttribute id="SOURCE_TYPE">
          <com:Text xml:lang="en"/>
        </gen:ReportedAttribute>
        <gen:ReportedAttribute id="COLL_METHOD">
          <com:Text xml:lang="en"/>
        </gen:ReportedAttribute>
        <gen:ReportedAttribute id="FREQ_COLL">
          <com:Text xml:lang="en"/>
        </gen:ReportedAttribute>
        <gen:ReportedAttribute id="REL_CAL_POLICY">
          <com:Text xml:lang="en"/>
        </gen:ReportedAttribute>
        <gen:ReportedAttribute id="DATA_SOURCE">
          <com:Text xml:lang="en"/>
        </gen:ReportedAttribute>
        <gen:ReportedAttribute id="COMPILING_ORG">
          <com:Text xml:lang="en"/>
        </gen:ReportedAttribute>
        <gen:ReportedAttribute id="INST_MANDATE">
          <com:Text xml:lang="en"/>
        </gen:ReportedAttribute>
        <gen:ReportedAttribute id="OTHER_METHOD">
          <com:Text xml:lang="en"/>
        </gen:ReportedAttribute>
        <gen:ReportedAttribute id="RATIONALE">
          <com:Text xml:lang="en"/>
        </gen:ReportedAttribute>
        <gen:ReportedAttribute id="REC_USE_LIM">
          <com:Text xml:lang="en"/>
        </gen:ReportedAttribute>
        <gen:ReportedAttribute id="DATA_COMP">
          <com:Text xml:lang="en"/>
        </gen:ReportedAttribute>
        <gen:ReportedAttribute id="DATA_VALIDATION">
          <com:Text xml:lang="en"/>
        </gen:ReportedAttribute>
        <gen:ReportedAttribute id="ADJUSTMENT">
          <com:Text xml:lang="en"/>
        </gen:ReportedAttribute>
        <gen:ReportedAttribute id="IMPUTATION">
          <com:Text xml:lang="en"/>
        </gen:ReportedAttribute>
        <gen:ReportedAttribute id="REG_AGG">
          <com:Text xml:lang="en"/>
        </gen:ReportedAttribute>
        <gen:ReportedAttribute id="DOC_METHOD">
          <com:Text xml:lang="en"/>
        </gen:ReportedAttribute>
        <gen:ReportedAttribute id="QUALITY_MGMNT">
          <com:Text xml:lang="en"/>
        </gen:ReportedAttribute>
        <gen:ReportedAttribute id="QUALITY_ASSURE">
          <com:Text xml:lang="en"/>
        </gen:ReportedAttribute>
        <gen:ReportedAttribute id="QUALITY_ASSMNT">
          <com:Text xml:lang="en"/>
        </gen:ReportedAttribute>
        <gen:ReportedAttribute id="COVERAGE">
          <com:Text xml:lang="en"/>
        </gen:ReportedAttribute>
        <gen:ReportedAttribute id="COMPARABILITY">
          <com:Text xml:lang="en"/>
        </gen:ReportedAttribute>
        <gen:ReportedAttribute id="OTHER_DOC">
          <com:Text xml:lang="en"/>
        </gen:ReportedAttribute>
      </gen:AttributeSet>
    </gen:Report>
  </mes:MetadataSet>
  <mes:MetadataSet structureRef="MDS1" setID="31e22e94-cfa5-488e-bb11-c381813e9027">
    <com:Name xml:lang="en">SDG METADATA SET</com:Name>
    <gen:Report id="SDG_META_RPT">
      <gen:Target id="KEY_TARGET">
        <gen:ReferenceValue id="DIMENSION_DESCRIPTOR_VALUES_TARGET">
          <gen:DataKey>
            <com:KeyValue id="SERIES">
              <com:Value>SE_AWP_CPRA</com:Value>
            </com:KeyValue>
            <com:KeyValue id="REPORTING_TYPE">
              <com:Value>N</com:Value>
            </com:KeyValue>
            <com:KeyValue id="REF_AREA">
              <com:Value>BI</com:Value>
            </com:KeyValue>
          </gen:DataKey>
        </gen:ReferenceValue>
        <gen:ReferenceValue id="Dataflow">
          <gen:ObjectReference>
            <URN>urn:sdmx:org.sdmx.infomodel.datastructure.Dataflow=IAEG-SDGs:DF_SDG_GLC(1.0)</URN>
          </gen:ObjectReference>
        </gen:ReferenceValue>
      </gen:Target>
      <gen:AttributeSet>
        <gen:ReportedAttribute id="SDG_INDICATOR_INFO">
          <com:Text xml:lang="en"/>
        </gen:ReportedAttribute>
        <gen:ReportedAttribute id="SDG_GOAL">
          <com:Text xml:lang="en"/>
        </gen:ReportedAttribute>
        <gen:ReportedAttribute id="SDG_TARGET">
          <com:Text xml:lang="en"/>
        </gen:ReportedAttribute>
        <gen:ReportedAttribute id="SDG_INDICATOR">
          <com:Text xml:lang="en"/>
        </gen:ReportedAttribute>
        <gen:ReportedAttribute id="SDG_SERIES_DESCR">
          <com:Text xml:lang="en"/>
        </gen:ReportedAttribute>
        <gen:ReportedAttribute id="META_LAST_UPDATE">
          <com:Text xml:lang="en"/>
        </gen:ReportedAttribute>
        <gen:ReportedAttribute id="SDG_RELATED_INDICATORS">
          <com:Text xml:lang="en"/>
        </gen:ReportedAttribute>
        <gen:ReportedAttribute id="SDG_CUSTODIAN_AGENCIES">
          <com:Text xml:lang="en"/>
        </gen:ReportedAttribute>
        <gen:ReportedAttribute id="CONTACT">
          <com:Text xml:lang="en"/>
        </gen:ReportedAttribute>
        <gen:ReportedAttribute id="CONTACT_ORGANISATION">
          <com:Text xml:lang="en"/>
        </gen:ReportedAttribute>
        <gen:ReportedAttribute id="CONTACT_NAME">
          <com:Text xml:lang="en"/>
        </gen:ReportedAttribute>
        <gen:ReportedAttribute id="ORGANISATION_UNIT">
          <com:Text xml:lang="en"/>
        </gen:ReportedAttribute>
        <gen:ReportedAttribute id="CONTACT_FUNCT">
          <com:Text xml:lang="en"/>
        </gen:ReportedAttribute>
        <gen:ReportedAttribute id="CONTACT_PHONE">
          <com:Text xml:lang="en"/>
        </gen:ReportedAttribute>
        <gen:ReportedAttribute id="CONTACT_MAIL">
          <com:Text xml:lang="en"/>
        </gen:ReportedAttribute>
        <gen:ReportedAttribute id="CONTACT_EMAIL">
          <com:Text xml:lang="en"/>
        </gen:ReportedAttribute>
        <gen:ReportedAttribute id="IND_DEF_CON_CLASS">
          <com:Text xml:lang="en"/>
        </gen:ReportedAttribute>
        <gen:ReportedAttribute id="STAT_CONC_DEF">
          <com:Text xml:lang="en"/>
        </gen:ReportedAttribute>
        <gen:ReportedAttribute id="UNIT_MEASURE">
          <com:Text xml:lang="en"/>
        </gen:ReportedAttribute>
        <gen:ReportedAttribute id="CLASS_SYSTEM">
          <com:Text xml:lang="en"/>
        </gen:ReportedAttribute>
        <gen:ReportedAttribute id="SRC_TYPE_COLL_METHOD">
          <com:Text xml:lang="en"/>
        </gen:ReportedAttribute>
        <gen:ReportedAttribute id="SOURCE_TYPE">
          <com:Text xml:lang="en"/>
        </gen:ReportedAttribute>
        <gen:ReportedAttribute id="COLL_METHOD">
          <com:Text xml:lang="en"/>
        </gen:ReportedAttribute>
        <gen:ReportedAttribute id="FREQ_COLL">
          <com:Text xml:lang="en"/>
        </gen:ReportedAttribute>
        <gen:ReportedAttribute id="REL_CAL_POLICY">
          <com:Text xml:lang="en"/>
        </gen:ReportedAttribute>
        <gen:ReportedAttribute id="DATA_SOURCE">
          <com:Text xml:lang="en"/>
        </gen:ReportedAttribute>
        <gen:ReportedAttribute id="COMPILING_ORG">
          <com:Text xml:lang="en"/>
        </gen:ReportedAttribute>
        <gen:ReportedAttribute id="INST_MANDATE">
          <com:Text xml:lang="en"/>
        </gen:ReportedAttribute>
        <gen:ReportedAttribute id="OTHER_METHOD">
          <com:Text xml:lang="en"/>
        </gen:ReportedAttribute>
        <gen:ReportedAttribute id="RATIONALE">
          <com:Text xml:lang="en"/>
        </gen:ReportedAttribute>
        <gen:ReportedAttribute id="REC_USE_LIM">
          <com:Text xml:lang="en"/>
        </gen:ReportedAttribute>
        <gen:ReportedAttribute id="DATA_COMP">
          <com:Text xml:lang="en"/>
        </gen:ReportedAttribute>
        <gen:ReportedAttribute id="DATA_VALIDATION">
          <com:Text xml:lang="en"/>
        </gen:ReportedAttribute>
        <gen:ReportedAttribute id="ADJUSTMENT">
          <com:Text xml:lang="en"/>
        </gen:ReportedAttribute>
        <gen:ReportedAttribute id="IMPUTATION">
          <com:Text xml:lang="en"/>
        </gen:ReportedAttribute>
        <gen:ReportedAttribute id="REG_AGG">
          <com:Text xml:lang="en"/>
        </gen:ReportedAttribute>
        <gen:ReportedAttribute id="DOC_METHOD">
          <com:Text xml:lang="en"/>
        </gen:ReportedAttribute>
        <gen:ReportedAttribute id="QUALITY_MGMNT">
          <com:Text xml:lang="en"/>
        </gen:ReportedAttribute>
        <gen:ReportedAttribute id="QUALITY_ASSURE">
          <com:Text xml:lang="en"/>
        </gen:ReportedAttribute>
        <gen:ReportedAttribute id="QUALITY_ASSMNT">
          <com:Text xml:lang="en"/>
        </gen:ReportedAttribute>
        <gen:ReportedAttribute id="COVERAGE">
          <com:Text xml:lang="en"/>
        </gen:ReportedAttribute>
        <gen:ReportedAttribute id="COMPARABILITY">
          <com:Text xml:lang="en"/>
        </gen:ReportedAttribute>
        <gen:ReportedAttribute id="OTHER_DOC">
          <com:Text xml:lang="en"/>
        </gen:ReportedAttribute>
      </gen:AttributeSet>
    </gen:Report>
  </mes:MetadataSet>
  <mes:MetadataSet structureRef="MDS1" setID="acdda6a8-f267-400d-813c-bccd7286b9ed">
    <com:Name xml:lang="en">SDG METADATA SET</com:Name>
    <gen:Report id="SDG_META_RPT">
      <gen:Target id="KEY_TARGET">
        <gen:ReferenceValue id="DIMENSION_DESCRIPTOR_VALUES_TARGET">
          <gen:DataKey>
            <com:KeyValue id="SERIES">
              <com:Value>SE_TOT_GPI_FS</com:Value>
            </com:KeyValue>
            <com:KeyValue id="REPORTING_TYPE">
              <com:Value>N</com:Value>
            </com:KeyValue>
            <com:KeyValue id="REF_AREA">
              <com:Value>BI</com:Value>
            </com:KeyValue>
          </gen:DataKey>
        </gen:ReferenceValue>
        <gen:ReferenceValue id="Dataflow">
          <gen:ObjectReference>
            <URN>urn:sdmx:org.sdmx.infomodel.datastructure.Dataflow=IAEG-SDGs:DF_SDG_GLC(1.0)</URN>
          </gen:ObjectReference>
        </gen:ReferenceValue>
      </gen:Target>
      <gen:AttributeSet>
        <gen:ReportedAttribute id="SDG_INDICATOR_INFO">
          <com:Text xml:lang="en"/>
        </gen:ReportedAttribute>
        <gen:ReportedAttribute id="SDG_GOAL">
          <com:Text xml:lang="en"/>
        </gen:ReportedAttribute>
        <gen:ReportedAttribute id="SDG_TARGET">
          <com:Text xml:lang="en"/>
        </gen:ReportedAttribute>
        <gen:ReportedAttribute id="SDG_INDICATOR">
          <com:Text xml:lang="en"/>
        </gen:ReportedAttribute>
        <gen:ReportedAttribute id="SDG_SERIES_DESCR">
          <com:Text xml:lang="en"/>
        </gen:ReportedAttribute>
        <gen:ReportedAttribute id="META_LAST_UPDATE">
          <com:Text xml:lang="en"/>
        </gen:ReportedAttribute>
        <gen:ReportedAttribute id="SDG_RELATED_INDICATORS">
          <com:Text xml:lang="en"/>
        </gen:ReportedAttribute>
        <gen:ReportedAttribute id="SDG_CUSTODIAN_AGENCIES">
          <com:Text xml:lang="en"/>
        </gen:ReportedAttribute>
        <gen:ReportedAttribute id="CONTACT">
          <com:Text xml:lang="en"/>
        </gen:ReportedAttribute>
        <gen:ReportedAttribute id="CONTACT_ORGANISATION">
          <com:Text xml:lang="en"/>
        </gen:ReportedAttribute>
        <gen:ReportedAttribute id="CONTACT_NAME">
          <com:Text xml:lang="en"/>
        </gen:ReportedAttribute>
        <gen:ReportedAttribute id="ORGANISATION_UNIT">
          <com:Text xml:lang="en"/>
        </gen:ReportedAttribute>
        <gen:ReportedAttribute id="CONTACT_FUNCT">
          <com:Text xml:lang="en"/>
        </gen:ReportedAttribute>
        <gen:ReportedAttribute id="CONTACT_PHONE">
          <com:Text xml:lang="en"/>
        </gen:ReportedAttribute>
        <gen:ReportedAttribute id="CONTACT_MAIL">
          <com:Text xml:lang="en"/>
        </gen:ReportedAttribute>
        <gen:ReportedAttribute id="CONTACT_EMAIL">
          <com:Text xml:lang="en"/>
        </gen:ReportedAttribute>
        <gen:ReportedAttribute id="IND_DEF_CON_CLASS">
          <com:Text xml:lang="en"/>
        </gen:ReportedAttribute>
        <gen:ReportedAttribute id="STAT_CONC_DEF">
          <com:Text xml:lang="en"/>
        </gen:ReportedAttribute>
        <gen:ReportedAttribute id="UNIT_MEASURE">
          <com:Text xml:lang="en"/>
        </gen:ReportedAttribute>
        <gen:ReportedAttribute id="CLASS_SYSTEM">
          <com:Text xml:lang="en"/>
        </gen:ReportedAttribute>
        <gen:ReportedAttribute id="SRC_TYPE_COLL_METHOD">
          <com:Text xml:lang="en"/>
        </gen:ReportedAttribute>
        <gen:ReportedAttribute id="SOURCE_TYPE">
          <com:Text xml:lang="en"/>
        </gen:ReportedAttribute>
        <gen:ReportedAttribute id="COLL_METHOD">
          <com:Text xml:lang="en"/>
        </gen:ReportedAttribute>
        <gen:ReportedAttribute id="FREQ_COLL">
          <com:Text xml:lang="en"/>
        </gen:ReportedAttribute>
        <gen:ReportedAttribute id="REL_CAL_POLICY">
          <com:Text xml:lang="en"/>
        </gen:ReportedAttribute>
        <gen:ReportedAttribute id="DATA_SOURCE">
          <com:Text xml:lang="en"/>
        </gen:ReportedAttribute>
        <gen:ReportedAttribute id="COMPILING_ORG">
          <com:Text xml:lang="en"/>
        </gen:ReportedAttribute>
        <gen:ReportedAttribute id="INST_MANDATE">
          <com:Text xml:lang="en"/>
        </gen:ReportedAttribute>
        <gen:ReportedAttribute id="OTHER_METHOD">
          <com:Text xml:lang="en"/>
        </gen:ReportedAttribute>
        <gen:ReportedAttribute id="RATIONALE">
          <com:Text xml:lang="en"/>
        </gen:ReportedAttribute>
        <gen:ReportedAttribute id="REC_USE_LIM">
          <com:Text xml:lang="en"/>
        </gen:ReportedAttribute>
        <gen:ReportedAttribute id="DATA_COMP">
          <com:Text xml:lang="en"/>
        </gen:ReportedAttribute>
        <gen:ReportedAttribute id="DATA_VALIDATION">
          <com:Text xml:lang="en"/>
        </gen:ReportedAttribute>
        <gen:ReportedAttribute id="ADJUSTMENT">
          <com:Text xml:lang="en"/>
        </gen:ReportedAttribute>
        <gen:ReportedAttribute id="IMPUTATION">
          <com:Text xml:lang="en"/>
        </gen:ReportedAttribute>
        <gen:ReportedAttribute id="REG_AGG">
          <com:Text xml:lang="en"/>
        </gen:ReportedAttribute>
        <gen:ReportedAttribute id="DOC_METHOD">
          <com:Text xml:lang="en"/>
        </gen:ReportedAttribute>
        <gen:ReportedAttribute id="QUALITY_MGMNT">
          <com:Text xml:lang="en"/>
        </gen:ReportedAttribute>
        <gen:ReportedAttribute id="QUALITY_ASSURE">
          <com:Text xml:lang="en"/>
        </gen:ReportedAttribute>
        <gen:ReportedAttribute id="QUALITY_ASSMNT">
          <com:Text xml:lang="en"/>
        </gen:ReportedAttribute>
        <gen:ReportedAttribute id="COVERAGE">
          <com:Text xml:lang="en"/>
        </gen:ReportedAttribute>
        <gen:ReportedAttribute id="COMPARABILITY">
          <com:Text xml:lang="en"/>
        </gen:ReportedAttribute>
        <gen:ReportedAttribute id="OTHER_DOC">
          <com:Text xml:lang="en"/>
        </gen:ReportedAttribute>
      </gen:AttributeSet>
    </gen:Report>
  </mes:MetadataSet>
  <mes:MetadataSet structureRef="MDS1" setID="5eda6bb5-41cf-4fca-86cf-1f61b3b4f056">
    <com:Name xml:lang="en">SDG METADATA SET</com:Name>
    <gen:Report id="SDG_META_RPT">
      <gen:Target id="KEY_TARGET">
        <gen:ReferenceValue id="DIMENSION_DESCRIPTOR_VALUES_TARGET">
          <gen:DataKey>
            <com:KeyValue id="SERIES">
              <com:Value>SE_TOT_SESPI_FS</com:Value>
            </com:KeyValue>
            <com:KeyValue id="REPORTING_TYPE">
              <com:Value>N</com:Value>
            </com:KeyValue>
            <com:KeyValue id="REF_AREA">
              <com:Value>BI</com:Value>
            </com:KeyValue>
          </gen:DataKey>
        </gen:ReferenceValue>
        <gen:ReferenceValue id="Dataflow">
          <gen:ObjectReference>
            <URN>urn:sdmx:org.sdmx.infomodel.datastructure.Dataflow=IAEG-SDGs:DF_SDG_GLC(1.0)</URN>
          </gen:ObjectReference>
        </gen:ReferenceValue>
      </gen:Target>
      <gen:AttributeSet>
        <gen:ReportedAttribute id="SDG_INDICATOR_INFO">
          <com:Text xml:lang="en"/>
        </gen:ReportedAttribute>
        <gen:ReportedAttribute id="SDG_GOAL">
          <com:Text xml:lang="en"/>
        </gen:ReportedAttribute>
        <gen:ReportedAttribute id="SDG_TARGET">
          <com:Text xml:lang="en"/>
        </gen:ReportedAttribute>
        <gen:ReportedAttribute id="SDG_INDICATOR">
          <com:Text xml:lang="en"/>
        </gen:ReportedAttribute>
        <gen:ReportedAttribute id="SDG_SERIES_DESCR">
          <com:Text xml:lang="en"/>
        </gen:ReportedAttribute>
        <gen:ReportedAttribute id="META_LAST_UPDATE">
          <com:Text xml:lang="en"/>
        </gen:ReportedAttribute>
        <gen:ReportedAttribute id="SDG_RELATED_INDICATORS">
          <com:Text xml:lang="en"/>
        </gen:ReportedAttribute>
        <gen:ReportedAttribute id="SDG_CUSTODIAN_AGENCIES">
          <com:Text xml:lang="en"/>
        </gen:ReportedAttribute>
        <gen:ReportedAttribute id="CONTACT">
          <com:Text xml:lang="en"/>
        </gen:ReportedAttribute>
        <gen:ReportedAttribute id="CONTACT_ORGANISATION">
          <com:Text xml:lang="en"/>
        </gen:ReportedAttribute>
        <gen:ReportedAttribute id="CONTACT_NAME">
          <com:Text xml:lang="en"/>
        </gen:ReportedAttribute>
        <gen:ReportedAttribute id="ORGANISATION_UNIT">
          <com:Text xml:lang="en"/>
        </gen:ReportedAttribute>
        <gen:ReportedAttribute id="CONTACT_FUNCT">
          <com:Text xml:lang="en"/>
        </gen:ReportedAttribute>
        <gen:ReportedAttribute id="CONTACT_PHONE">
          <com:Text xml:lang="en"/>
        </gen:ReportedAttribute>
        <gen:ReportedAttribute id="CONTACT_MAIL">
          <com:Text xml:lang="en"/>
        </gen:ReportedAttribute>
        <gen:ReportedAttribute id="CONTACT_EMAIL">
          <com:Text xml:lang="en"/>
        </gen:ReportedAttribute>
        <gen:ReportedAttribute id="IND_DEF_CON_CLASS">
          <com:Text xml:lang="en"/>
        </gen:ReportedAttribute>
        <gen:ReportedAttribute id="STAT_CONC_DEF">
          <com:Text xml:lang="en"/>
        </gen:ReportedAttribute>
        <gen:ReportedAttribute id="UNIT_MEASURE">
          <com:Text xml:lang="en"/>
        </gen:ReportedAttribute>
        <gen:ReportedAttribute id="CLASS_SYSTEM">
          <com:Text xml:lang="en"/>
        </gen:ReportedAttribute>
        <gen:ReportedAttribute id="SRC_TYPE_COLL_METHOD">
          <com:Text xml:lang="en"/>
        </gen:ReportedAttribute>
        <gen:ReportedAttribute id="SOURCE_TYPE">
          <com:Text xml:lang="en"/>
        </gen:ReportedAttribute>
        <gen:ReportedAttribute id="COLL_METHOD">
          <com:Text xml:lang="en"/>
        </gen:ReportedAttribute>
        <gen:ReportedAttribute id="FREQ_COLL">
          <com:Text xml:lang="en"/>
        </gen:ReportedAttribute>
        <gen:ReportedAttribute id="REL_CAL_POLICY">
          <com:Text xml:lang="en"/>
        </gen:ReportedAttribute>
        <gen:ReportedAttribute id="DATA_SOURCE">
          <com:Text xml:lang="en"/>
        </gen:ReportedAttribute>
        <gen:ReportedAttribute id="COMPILING_ORG">
          <com:Text xml:lang="en"/>
        </gen:ReportedAttribute>
        <gen:ReportedAttribute id="INST_MANDATE">
          <com:Text xml:lang="en"/>
        </gen:ReportedAttribute>
        <gen:ReportedAttribute id="OTHER_METHOD">
          <com:Text xml:lang="en"/>
        </gen:ReportedAttribute>
        <gen:ReportedAttribute id="RATIONALE">
          <com:Text xml:lang="en"/>
        </gen:ReportedAttribute>
        <gen:ReportedAttribute id="REC_USE_LIM">
          <com:Text xml:lang="en"/>
        </gen:ReportedAttribute>
        <gen:ReportedAttribute id="DATA_COMP">
          <com:Text xml:lang="en"/>
        </gen:ReportedAttribute>
        <gen:ReportedAttribute id="DATA_VALIDATION">
          <com:Text xml:lang="en"/>
        </gen:ReportedAttribute>
        <gen:ReportedAttribute id="ADJUSTMENT">
          <com:Text xml:lang="en"/>
        </gen:ReportedAttribute>
        <gen:ReportedAttribute id="IMPUTATION">
          <com:Text xml:lang="en"/>
        </gen:ReportedAttribute>
        <gen:ReportedAttribute id="REG_AGG">
          <com:Text xml:lang="en"/>
        </gen:ReportedAttribute>
        <gen:ReportedAttribute id="DOC_METHOD">
          <com:Text xml:lang="en"/>
        </gen:ReportedAttribute>
        <gen:ReportedAttribute id="QUALITY_MGMNT">
          <com:Text xml:lang="en"/>
        </gen:ReportedAttribute>
        <gen:ReportedAttribute id="QUALITY_ASSURE">
          <com:Text xml:lang="en"/>
        </gen:ReportedAttribute>
        <gen:ReportedAttribute id="QUALITY_ASSMNT">
          <com:Text xml:lang="en"/>
        </gen:ReportedAttribute>
        <gen:ReportedAttribute id="COVERAGE">
          <com:Text xml:lang="en"/>
        </gen:ReportedAttribute>
        <gen:ReportedAttribute id="COMPARABILITY">
          <com:Text xml:lang="en"/>
        </gen:ReportedAttribute>
        <gen:ReportedAttribute id="OTHER_DOC">
          <com:Text xml:lang="en"/>
        </gen:ReportedAttribute>
      </gen:AttributeSet>
    </gen:Report>
  </mes:MetadataSet>
</mes:GenericMetadata>