{"status":"success","message":"All metadata fields for indicator 4-4-1, translated into all languages","data":{"en":"Goal 4. Ensure equitable, inclusive and quality education and lifelong learning opportunities for all4.4 By 2030, significantly increase the number of young people and adults with the skills, including technical and vocational skills, necessary for employment, decent work and entrepreneurship4.4.1. % of 6th year leavers enrolled in CEMs (public and private)Proportion of students entering vocational training centers compared to all students having completed 6 th%Ratio between students entering Trades Education Centers and all students having completed 6th grade, multiplied by 100.Not available","fr":"Objectif 4. Assurer à tous une éducation équitable, inclusive et de qualité et des possibilités d’apprentissage tout au long de la vie4.4 D’ici à 2030, augmenter nettement le nombre de jeunes et d’adultes disposant des compétences, notamment techniques et professionnelles, nécessaires à l’emploi, à l’obtention d’un travail décent et à l’entrepreneuriat4.4.1. % des sortants de 6ème année scolarisés dans les CEM (public et privés)Proportion de élèves entrant dans les Centre d'Enseignement des Métiers par rapport à tous les élèves ayant terminé la 6 ème%Rapport entre les élèves entrant dans les Centres d'Enseignement des Métiers et tous les élèves ayant terminé la 6 ème, multiplié par 100.Non disponible"}}